rtl/argmax.v
`timescale 1ns / 1ps
// =============================================================
// ARGMAX : Tim chi so lop co gia tri logit lon nhat (47 lop)
// =============================================================
module argmax (
    input  wire        clk,
    input  wire        rst_n,

    input  wire        start,
    output wire        ready,
    output reg         done,

    // Cong ghi vector logit dau vao (47 phan tu, 32-bit co dau)
    input  wire        in_wr_en,
    input  wire [5:0]  in_wr_addr,
    input  wire signed [31:0] in_wr_data,

    output reg  [5:0]  predicted_class,
    output reg         valid_out
);

    reg signed [31:0] fc3_out [0:46];

    always @(posedge clk) begin
        if (in_wr_en) fc3_out[in_wr_addr] <= in_wr_data;
    end

    localparam IDLE = 0, INIT = 1, COMP = 2;
    reg [1:0] state;

    reg [15:0] c;
    reg signed [31:0] max_val;
    reg [5:0] max_idx;

    assign ready = (state == IDLE);

    always @(posedge clk or negedge rst_n) begin
        if (!rst_n) begin
            state           <= IDLE;
            done            <= 0;
            valid_out       <= 0;
            predicted_class <= 0;
        end else begin
            done      <= 0;
            valid_out <= 0;
            case (state)
                IDLE: begin
                    if (start) begin
                        c <= 1;
                        state <= INIT;
                    end
                end

                INIT: begin
                    max_val <= fc3_out[0];
                    max_idx <= 0;
                    state   <= COMP;
                end

                COMP: begin
                    if (fc3_out[c] > max_val) begin
                        max_val <= fc3_out[c];
                        max_idx <= c[5:0];
                    end

                    if (c == 46) begin
                        predicted_class <= (fc3_out[c] > max_val) ? c[5:0] : max_idx;
                        valid_out <= 1;
                        done      <= 1;
                        state     <= IDLE;
                    end else begin
                        c <= c + 1;
                    end
                end
            endcase
        end
    end
endmodule

testbench/tb_argmax.v
`timescale 1ns / 1ps
// =============================================================
// TB_ARGMAX : Kiem tra doc lap module argmax (47 lop)
// Chay nhieu vector logit ngau nhien, doi chieu voi phep tinh
// argmax tham chieu (uu tien chi so nho hon khi bang nhau).
// =============================================================
module tb_argmax;

    reg clk, rst_n, start;
    wire ready, done;

    reg         in_wr_en;
    reg [5:0]   in_wr_addr;
    reg signed [31:0] in_wr_data;

    wire [5:0] predicted_class;
    wire       valid_out;

    argmax dut (
        .clk(clk), .rst_n(rst_n),
        .start(start), .ready(ready), .done(done),
        .in_wr_en(in_wr_en), .in_wr_addr(in_wr_addr), .in_wr_data(in_wr_data),
        .predicted_class(predicted_class), .valid_out(valid_out)
    );

    initial clk = 0;
    always #5 clk = ~clk;

    // Xuat waveform ra file .vcd de xem bang GTKWave
    initial begin
        $dumpfile("argmax.vcd");
        $dumpvars(0, tb_argmax);
    end

    reg signed [31:0] logits [0:46];
    integer t, i, errors;
    integer ref_idx;
    reg signed [31:0] ref_max;

    initial begin
        rst_n = 0; start = 0; in_wr_en = 0; in_wr_addr = 0; in_wr_data = 0;
        errors = 0;

        repeat (3) @(posedge clk);
        @(negedge clk); rst_n = 1;

        for (t = 0; t < 20; t = t + 1) begin
            // Sinh 47 logit ngau nhien (co the am/duong)
            for (i = 0; i < 47; i = i + 1)
                logits[i] = $random % 1000;

            // Tinh argmax tham chieu: giu chi so dau tien dat max
            ref_max = logits[0];
            ref_idx = 0;
            for (i = 1; i < 47; i = i + 1)
                if (logits[i] > ref_max) begin
                    ref_max = logits[i];
                    ref_idx = i;
                end

            @(negedge clk);
            for (i = 0; i < 47; i = i + 1) begin
                in_wr_en   = 1;
                in_wr_addr = i[5:0];
                in_wr_data = logits[i];
                @(negedge clk);
            end
            in_wr_en = 0;

            wait (ready);
            @(negedge clk); start = 1;
            @(negedge clk); start = 0;

            wait (valid_out);
            #1;
            if (predicted_class !== ref_idx[5:0]) begin
                errors = errors + 1;
                $display("[SAI] test=%0d rtl=%0d ref=%0d", t, predicted_class, ref_idx);
            end
            @(negedge clk);
        end

        if (errors == 0)
            $display("\n[PASS] argmax: tat ca %0d test ngau nhien deu dung.\n", t);
        else
            $display("\n[FAIL] argmax: %0d / %0d test sai.\n", errors, t);

        #20 $finish;
    end

    initial begin
        #200000;
        $display("[WATCHDOG] tb_argmax qua thoi gian cho!");
        $finish;
    end
endmodule

results/argmax.vcd
$date
	Thu Jul 23 23:59:49 2026
$end
$version
	Icarus Verilog
$end
$timescale
	1ps
$end
$scope module tb_argmax $end
$var wire 1 ! valid_out $end
$var wire 1 " ready $end
$var wire 6 # predicted_class [5:0] $end
$var wire 1 $ done $end
$var reg 1 % clk $end
$var reg 6 & in_wr_addr [5:0] $end
$var reg 32 ' in_wr_data [31:0] $end
$var reg 1 ( in_wr_en $end
$var reg 32 ) ref_max [31:0] $end
$var reg 1 * rst_n $end
$var reg 1 + start $end
$var integer 32 , errors [31:0] $end
$var integer 32 - i [31:0] $end
$var integer 32 . ref_idx [31:0] $end
$var integer 32 / t [31:0] $end
$scope module dut $end
$var wire 1 % clk $end
$var wire 6 0 in_wr_addr [5:0] $end
$var wire 32 1 in_wr_data [31:0] $end
$var wire 1 ( in_wr_en $end
$var wire 1 * rst_n $end
$var wire 1 + start $end
$var wire 1 " ready $end
$var reg 16 2 c [15:0] $end
$var reg 1 $ done $end
$var reg 6 3 max_idx [5:0] $end
$var reg 32 4 max_val [31:0] $end
$var reg 6 5 predicted_class [5:0] $end
$var reg 2 6 state [1:0] $end
$var reg 1 ! valid_out $end
$upscope $end
$upscope $end
$enddefinitions $end
#0
$dumpvars
b0 6
b0 5
bx 4
bx 3
bx 2
b0 1
b0 0
bx /
bx .
bx -
b0 ,
0+
0*
bx )
0(
b0 '
b0 &
0%
0$
b0 #
1"
0!
$end
#5000
1%
#10000
0%
#15000
1%
#20000
0%
#25000
1%
#30000
b10110 .
b1111011010 )
b101111 -
b0 /
1*
0%
#35000
1%
#40000
b1011101100 '
b1011101100 1
1(
b0 -
0%
#45000
1%
#50000
b11111111111111111111111100111001 '
b11111111111111111111111100111001 1
b1 &
b1 0
b1 -
0%
#55000
1%
#60000
b11111111111111111111111100010001 '
b11111111111111111111111100010001 1
b10 &
b10 0
b10 -
0%
#65000
1%
#70000
b11111111111111111111111011001011 '
b11111111111111111111111011001011 1
b11 &
b11 0
b11 -
0%
#75000
1%
#80000
b1110111101 '
b1110111101 1
b100 &
b100 0
b100 -
0%
#85000
1%
#90000
b101 &
b101 0
b101 -
0%
#95000
1%
#100000
b11111111111111111111110000110101 '
b11111111111111111111110000110101 1
b110 &
b110 0
b110 -
0%
#105000
1%
#110000
b11111111111111111111111100101010 '
b11111111111111111111111100101010 1
b111 &
b111 0
b111 -
0%
#115000
1%
#120000
b101101001 '
b101101001 1
b1000 &
b1000 0
b1000 -
0%
#125000
1%
#130000
b11101 '
b11101 1
b1001 &
b1001 0
b1001 -
0%
#135000
1%
#140000
b100111110 '
b100111110 1
b1010 &
b1010 0
b1010 -
0%
#145000
1%
#150000
b1001010101 '
b1001010101 1
b1011 &
b1011 0
b1011 -
0%
#155000
1%
#160000
b1001110101 '
b1001110101 1
b1100 &
b1100 0
b1100 -
0%
#165000
1%
#170000
b1001100100 '
b1001100100 1
b1101 &
b1101 0
b1101 -
0%
#175000
1%
#180000
b100100001 '
b100100001 1
b1110 &
b1110 0
b1110 -
0%
#185000
1%
#190000
b11111111111111111111111010001110 '
b11111111111111111111111010001110 1
b1111 &
b1111 0
b1111 -
0%
#195000
1%
#200000
b11111111111111111111111110011101 '
b11111111111111111111111110011101 1
b10000 &
b10000 0
b10000 -
0%
#205000
1%
#210000
b11111111111111111111111101010010 '
b11111111111111111111111101010010 1
b10001 &
b10001 0
b10001 -
0%
#215000
1%
#220000
b1101110101 '
b1101110101 1
b10010 &
b10010 0
b10010 -
0%
#225000
1%
#230000
b11111111111111111111111111010111 '
b11111111111111111111111111010111 1
b10011 &
b10011 0
b10011 -
0%
#235000
1%
#240000
b11111111111111111111111110011010 '
b11111111111111111111111110011010 1
b10100 &
b10100 0
b10100 -
0%
#245000
1%
#250000
b100111 '
b100111 1
b10101 &
b10101 0
b10101 -
0%
#255000
1%
#260000
b1111011010 '
b1111011010 1
b10110 &
b10110 0
b10110 -
0%
#265000
1%
#270000
b11111111111111111111110111011110 '
b11111111111111111111110111011110 1
b10111 &
b10111 0
b10111 -
0%
#275000
1%
#280000
b11111111111111111111111110000000 '
b11111111111111111111111110000000 1
b11000 &
b11000 0
b11000 -
0%
#285000
1%
#290000
b11111111111111111111111111010101 '
b11111111111111111111111111010101 1
b11001 &
b11001 0
b11001 -
0%
#295000
1%
#300000
b1101110100 '
b1101110100 1
b11010 &
b11010 0
b11010 -
0%
#305000
1%
#310000
b11111111111111111111110011011101 '
b11111111111111111111110011011101 1
b11011 &
b11011 0
b11011 -
0%
#315000
1%
#320000
b11111111111111111111110101100101 '
b11111111111111111111110101100101 1
b11100 &
b11100 0
b11100 -
0%
#325000
1%
#330000
b11111111111111111111111000000101 '
b11111111111111111111111000000101 1
b11101 &
b11101 0
b11101 -
0%
#335000
1%
#340000
b11111111111111111111110011111011 '
b11111111111111111111110011111011 1
b11110 &
b11110 0
b11110 -
0%
#345000
1%
#350000
b100100010 '
b100100010 1
b11111 &
b11111 0
b11111 -
0%
#355000
1%
#360000
b11111111111111111111111010010000 '
b11111111111111111111111010010000 1
b100000 &
b100000 0
b100000 -
0%
#365000
1%
#370000
b1000011000 '
b1000011000 1
b100001 &
b100001 0
b100001 -
0%
#375000
1%
#380000
b1000000010 '
b1000000010 1
b100010 &
b100010 0
b100010 -
0%
#385000
1%
#390000
b11111111111111111111111110110101 '
b11111111111111111111111110110101 1
b100011 &
b100011 0
b100011 -
0%
#395000
1%
#400000
b11111111111111111111111011101110 '
b11111111111111111111111011101110 1
b100100 &
b100100 0
b100100 -
0%
#405000
1%
#410000
b11111111111111111111111010010011 '
b11111111111111111111111010010011 1
b100101 &
b100101 0
b100101 -
0%
#415000
1%
#420000
b11111111111111111111111100010101 '
b11111111111111111111111100010101 1
b100110 &
b100110 0
b100110 -
0%
#425000
1%
#430000
b11111111111111111111111001100011 '
b11111111111111111111111001100011 1
b100111 &
b100111 0
b100111 -
0%
#435000
1%
#440000
b101100011 '
b101100011 1
b101000 &
b101000 0
b101000 -
0%
#445000
1%
#450000
b11111111111111111111110011010101 '
b11111111111111111111110011010101 1
b101001 &
b101001 0
b101001 -
0%
#455000
1%
#460000
b11111111111111111111111101100010 '
b11111111111111111111111101100010 1
b101010 &
b101010 0
b101010 -
0%
#465000
1%
#470000
b11111111111111111111110100110110 '
b11111111111111111111110100110110 1
b101011 &
b101011 0
b101011 -
0%
#475000
1%
#480000
b101111101 '
b101111101 1
b101100 &
b101100 0
b101100 -
0%
#485000
1%
#490000
b11111111111111111111111001011111 '
b11111111111111111111111001011111 1
b101101 &
b101101 0
b101101 -
0%
#495000
1%
#500000
b10010011 '
b10010011 1
b101110 &
b101110 0
b101110 -
0%
#505000
1%
#510000
0(
b101111 -
0%
#515000
1%
#520000
1+
0%
#525000
0"
b1 6
b1 2
1%
#530000
0+
0%
#535000
b10 6
b0 3
b1011101100 4
1%
#540000
0%
#545000
b10 2
1%
#550000
0%
#555000
b11 2
1%
#560000
0%
#565000
b100 2
1%
#570000
0%
#575000
b101 2
b100 3
b1110111101 4
1%
#580000
0%
#585000
b110 2
1%
#590000
0%
#595000
b111 2
1%
#600000
0%
#605000
b1000 2
1%
#610000
0%
#615000
b1001 2
1%
#620000
0%
#625000
b1010 2
1%
#630000
0%
#635000
b1011 2
1%
#640000
0%
#645000
b1100 2
1%
#650000
0%
#655000
b1101 2
1%
#660000
0%
#665000
b1110 2
1%
#670000
0%
#675000
b1111 2
1%
#680000
0%
#685000
b10000 2
1%
#690000
0%
#695000
b10001 2
1%
#700000
0%
#705000
b10010 2
1%
#710000
0%
#715000
b10011 2
1%
#720000
0%
#725000
b10100 2
1%
#730000
0%
#735000
b10101 2
1%
#740000
0%
#745000
b10110 2
1%
#750000
0%
#755000
b10111 2
b10110 3
b1111011010 4
1%
#760000
0%
#765000
b11000 2
1%
#770000
0%
#775000
b11001 2
1%
#780000
0%
#785000
b11010 2
1%
#790000
0%
#795000
b11011 2
1%
#800000
0%
#805000
b11100 2
1%
#810000
0%
#815000
b11101 2
1%
#820000
0%
#825000
b11110 2
1%
#830000
0%
#835000
b11111 2
1%
#840000
0%
#845000
b100000 2
1%
#850000
0%
#855000
b100001 2
1%
#860000
0%
#865000
b100010 2
1%
#870000
0%
#875000
b100011 2
1%
#880000
0%
#885000
b100100 2
1%
#890000
0%
#895000
b100101 2
1%
#900000
0%
#905000
b100110 2
1%
#910000
0%
#915000
b100111 2
1%
#920000
0%
#925000
b101000 2
1%
#930000
0%
#935000
b101001 2
1%
#940000
0%
#945000
b101010 2
1%
#950000
0%
#955000
b101011 2
1%
#960000
0%
#965000
b101100 2
1%
#970000
0%
#975000
b101101 2
1%
#980000
0%
#985000
b101110 2
1%
#990000
0%
#995000
1"
b0 6
1$
1!
b10110 #
b10110 5
1%
#1000000
b10010 .
b1111001111 )
b101111 -
b1 /
0%
#1005000
0!
0$
1%
#1010000
b1100000010 '
b1100000010 1
b0 &
b0 0
1(
b0 -
0%
#1015000
1%
#1020000
b11111111111111111111111001010010 '
b11111111111111111111111001010010 1
b1 &
b1 0
b1 -
0%
#1025000
1%
#1030000
b11111111111111111111111001111100 '
b11111111111111111111111001111100 1
b10 &
b10 0
b10 -
0%
#1035000
1%
#1040000
b111111010 '
b111111010 1
b11 &
b11 0
b11 -
0%
#1045000
1%
#1050000
b1000010010 '
b1000010010 1
b100 &
b100 0
b100 -
0%
#1055000
1%
#1060000
b1101011001 '
b1101011001 1
b101 &
b101 0
b101 -
0%
#1065000
1%
#1070000
b11111111111111111111110110110000 '
b11111111111111111111110110110000 1
b110 &
b110 0
b110 -
0%
#1075000
1%
#1080000
b110111000 '
b110111000 1
b111 &
b111 0
b111 -
0%
#1085000
1%
#1090000
b11111111111111111111111100001001 '
b11111111111111111111111100001001 1
b1000 &
b1000 0
b1000 -
0%
#1095000
1%
#1100000
b110101011 '
b110101011 1
b1001 &
b1001 0
b1001 -
0%
#1105000
1%
#1110000
b1011111110 '
b1011111110 1
b1010 &
b1010 0
b1010 -
0%
#1115000
1%
#1120000
b1000001110 '
b1000001110 1
b1011 &
b1011 0
b1011 -
0%
#1125000
1%
#1130000
b1010110 '
b1010110 1
b1100 &
b1100 0
b1100 -
0%
#1135000
1%
#1140000
b11111111111111111111110001011100 '
b11111111111111111111110001011100 1
b1101 &
b1101 0
b1101 -
0%
#1145000
1%
#1150000
b11000010 '
b11000010 1
b1110 &
b1110 0
b1110 -
0%
#1155000
1%
#1160000
b11111111111111111111110010000011 '
b11111111111111111111110010000011 1
b1111 &
b1111 0
b1111 -
0%
#1165000
1%
#1170000
b11111111111111111111110010100001 '
b11111111111111111111110010100001 1
b10000 &
b10000 0
b10000 -
0%
#1175000
1%
#1180000
b1011100101 '
b1011100101 1
b10001 &
b10001 0
b10001 -
0%
#1185000
1%
#1190000
b1111001111 '
b1111001111 1
b10010 &
b10010 0
b10010 -
0%
#1195000
1%
#1200000
b11111111111111111111111001101011 '
b11111111111111111111111001101011 1
b10011 &
b10011 0
b10011 -
0%
#1205000
1%
#1210000
b1001010010 '
b1001010010 1
b10100 &
b10100 0
b10100 -
0%
#1215000
1%
#1220000
b11111111111111111111111010011110 '
b11111111111111111111111010011110 1
b10101 &
b10101 0
b10101 -
0%
#1225000
1%
#1230000
b111110101 '
b111110101 1
b10110 &
b10110 0
b10110 -
0%
#1235000
1%
#1240000
b10011001 '
b10011001 1
b10111 &
b10111 0
b10111 -
0%
#1245000
1%
#1250000
b101101001 '
b101101001 1
b11000 &
b11000 0
b11000 -
0%
#1255000
1%
#1260000
b11101010 '
b11101010 1
b11001 &
b11001 0
b11001 -
0%
#1265000
1%
#1270000
b1110110100 '
b1110110100 1
b11010 &
b11010 0
b11010 -
0%
#1275000
1%
#1280000
b100010111 '
b100010111 1
b11011 &
b11011 0
b11011 -
0%
#1285000
1%
#1290000
b1101010111 '
b1101010111 1
b11100 &
b11100 0
b11100 -
0%
#1295000
1%
#1300000
b1011010000 '
b1011010000 1
b11101 &
b11101 0
b11101 -
0%
#1305000
1%
#1310000
b11111111111111111111111010011111 '
b11111111111111111111111010011111 1
b11110 &
b11110 0
b11110 -
0%
#1315000
1%
#1320000
b11111 &
b11111 0
b11111 -
0%
#1325000
1%
#1330000
b11111111111111111111110100100100 '
b11111111111111111111110100100100 1
b100000 &
b100000 0
b100000 -
0%
#1335000
1%
#1340000
b11111111111111111111110010010011 '
b11111111111111111111110010010011 1
b100001 &
b100001 0
b100001 -
0%
#1345000
1%
#1350000
b1110000001 '
b1110000001 1
b100010 &
b100010 0
b100010 -
0%
#1355000
1%
#1360000
b11111111111111111111110100100001 '
b11111111111111111111110100100001 1
b100011 &
b100011 0
b100011 -
0%
#1365000
1%
#1370000
b11111111111111111111111010101000 '
b11111111111111111111111010101000 1
b100100 &
b100100 0
b100100 -
0%
#1375000
1%
#1380000
b11111111111111111111111111100111 '
b11111111111111111111111111100111 1
b100101 &
b100101 0
b100101 -
0%
#1385000
1%
#1390000
b11111111111111111111110100010001 '
b11111111111111111111110100010001 1
b100110 &
b100110 0
b100110 -
0%
#1395000
1%
#1400000
b1000110 '
b1000110 1
b100111 &
b100111 0
b100111 -
0%
#1405000
1%
#1410000
b101101100 '
b101101100 1
b101000 &
b101000 0
b101000 -
0%
#1415000
1%
#1420000
b11111111111111111111111101001010 '
b11111111111111111111111101001010 1
b101001 &
b101001 0
b101001 -
0%
#1425000
1%
#1430000
b1101000 '
b1101000 1
b101010 &
b101010 0
b101010 -
0%
#1435000
1%
#1440000
b11111111111111111111111110111111 '
b11111111111111111111111110111111 1
b101011 &
b101011 0
b101011 -
0%
#1445000
1%
#1450000
b1110011101 '
b1110011101 1
b101100 &
b101100 0
b101100 -
0%
#1455000
1%
#1460000
b111001010 '
b111001010 1
b101101 &
b101101 0
b101101 -
0%
#1465000
1%
#1470000
b11111111111111111111111100010110 '
b11111111111111111111111100010110 1
b101110 &
b101110 0
b101110 -
0%
#1475000
1%
#1480000
0(
b101111 -
0%
#1485000
1%
#1490000
1+
0%
#1495000
0"
b1 6
b1 2
1%
#1500000
0+
0%
#1505000
b10 6
b0 3
b1100000010 4
1%
#1510000
0%
#1515000
b10 2
1%
#1520000
0%
#1525000
b11 2
1%
#1530000
0%
#1535000
b100 2
1%
#1540000
0%
#1545000
b101 2
1%
#1550000
0%
#1555000
b110 2
b101 3
b1101011001 4
1%
#1560000
0%
#1565000
b111 2
1%
#1570000
0%
#1575000
b1000 2
1%
#1580000
0%
#1585000
b1001 2
1%
#1590000
0%
#1595000
b1010 2
1%
#1600000
0%
#1605000
b1011 2
1%
#1610000
0%
#1615000
b1100 2
1%
#1620000
0%
#1625000
b1101 2
1%
#1630000
0%
#1635000
b1110 2
1%
#1640000
0%
#1645000
b1111 2
1%
#1650000
0%
#1655000
b10000 2
1%
#1660000
0%
#1665000
b10001 2
1%
#1670000
0%
#1675000
b10010 2
1%
#1680000
0%
#1685000
b10011 2
b10010 3
b1111001111 4
1%
#1690000
0%
#1695000
b10100 2
1%
#1700000
0%
#1705000
b10101 2
1%
#1710000
0%
#1715000
b10110 2
1%
#1720000
0%
#1725000
b10111 2
1%
#1730000
0%
#1735000
b11000 2
1%
#1740000
0%
#1745000
b11001 2
1%
#1750000
0%
#1755000
b11010 2
1%
#1760000
0%
#1765000
b11011 2
1%
#1770000
0%
#1775000
b11100 2
1%
#1780000
0%
#1785000
b11101 2
1%
#1790000
0%
#1795000
b11110 2
1%
#1800000
0%
#1805000
b11111 2
1%
#1810000
0%
#1815000
b100000 2
1%
#1820000
0%
#1825000
b100001 2
1%
#1830000
0%
#1835000
b100010 2
1%
#1840000
0%
#1845000
b100011 2
1%
#1850000
0%
#1855000
b100100 2
1%
#1860000
0%
#1865000
b100101 2
1%
#1870000
0%
#1875000
b100110 2
1%
#1880000
0%
#1885000
b100111 2
1%
#1890000
0%
#1895000
b101000 2
1%
#1900000
0%
#1905000
b101001 2
1%
#1910000
0%
#1915000
b101010 2
1%
#1920000
0%
#1925000
b101011 2
1%
#1930000
0%
#1935000
b101100 2
1%
#1940000
0%
#1945000
b101101 2
1%
#1950000
0%
#1955000
b101110 2
1%
#1960000
0%
#1965000
1"
b0 6
1$
1!
b10010 #
b10010 5
1%
#1970000
b100001 .
b1110111100 )
b101111 -
b10 /
0%
#1975000
0!
0$
1%
#1980000
b1000011101 '
b1000011101 1
b0 &
b0 0
1(
b0 -
0%
#1985000
1%
#1990000
b1000101001 '
b1000101001 1
b1 &
b1 0
b1 -
0%
#1995000
1%
#2000000
b110110111 '
b110110111 1
b10 &
b10 0
b10 -
0%
#2005000
1%
#2010000
b11111111111111111111110011001011 '
b11111111111111111111110011001011 1
b11 &
b11 0
b11 -
0%
#2015000
1%
#2020000
b1011011101 '
b1011011101 1
b100 &
b100 0
b100 -
0%
#2025000
1%
#2030000
b11111111111111111111111111100000 '
b11111111111111111111111111100000 1
b101 &
b101 0
b101 -
0%
#2035000
1%
#2040000
b110111011 '
b110111011 1
b110 &
b110 0
b110 -
0%
#2045000
1%
#2050000
b1000101001 '
b1000101001 1
b111 &
b111 0
b111 -
0%
#2055000
1%
#2060000
b11111111111111111111110110000111 '
b11111111111111111111110110000111 1
b1000 &
b1000 0
b1000 -
0%
#2065000
1%
#2070000
b1100101010 '
b1100101010 1
b1001 &
b1001 0
b1001 -
0%
#2075000
1%
#2080000
b11000000 '
b11000000 1
b1010 &
b1010 0
b1010 -
0%
#2085000
1%
#2090000
b11111111111111111111110001010110 '
b11111111111111111111110001010110 1
b1011 &
b1011 0
b1011 -
0%
#2095000
1%
#2100000
b11111111111111111111111101011110 '
b11111111111111111111111101011110 1
b1100 &
b1100 0
b1100 -
0%
#2105000
1%
#2110000
b11111111111111111111111000001100 '
b11111111111111111111111000001100 1
b1101 &
b1101 0
b1101 -
0%
#2115000
1%
#2120000
b1100111010 '
b1100111010 1
b1110 &
b1110 0
b1110 -
0%
#2125000
1%
#2130000
b11111111111111111111111010000110 '
b11111111111111111111111010000110 1
b1111 &
b1111 0
b1111 -
0%
#2135000
1%
#2140000
b1011001011 '
b1011001011 1
b10000 &
b10000 0
b10000 -
0%
#2145000
1%
#2150000
b11111111111111111111111001101011 '
b11111111111111111111111001101011 1
b10001 &
b10001 0
b10001 -
0%
#2155000
1%
#2160000
b11111111111111111111110110010111 '
b11111111111111111111110110010111 1
b10010 &
b10010 0
b10010 -
0%
#2165000
1%
#2170000
b11111111111111111111111011001011 '
b11111111111111111111111011001011 1
b10011 &
b10011 0
b10011 -
0%
#2175000
1%
#2180000
b11111111111111111111110110011111 '
b11111111111111111111110110011111 1
b10100 &
b10100 0
b10100 -
0%
#2185000
1%
#2190000
b1011001100 '
b1011001100 1
b10101 &
b10101 0
b10101 -
0%
#2195000
1%
#2200000
b111111111 '
b111111111 1
b10110 &
b10110 0
b10110 -
0%
#2205000
1%
#2210000
b11111111111111111111110100101011 '
b11111111111111111111110100101011 1
b10111 &
b10111 0
b10111 -
0%
#2215000
1%
#2220000
b11111111111111111111111110011110 '
b11111111111111111111111110011110 1
b11000 &
b11000 0
b11000 -
0%
#2225000
1%
#2230000
b100111010 '
b100111010 1
b11001 &
b11001 0
b11001 -
0%
#2235000
1%
#2240000
b1011010001 '
b1011010001 1
b11010 &
b11010 0
b11010 -
0%
#2245000
1%
#2250000
b11111111111111111111111001111101 '
b11111111111111111111111001111101 1
b11011 &
b11011 0
b11011 -
0%
#2255000
1%
#2260000
b11111111111111111111110100010010 '
b11111111111111111111110100010010 1
b11100 &
b11100 0
b11100 -
0%
#2265000
1%
#2270000
b11111111111111111111110001011101 '
b11111111111111111111110001011101 1
b11101 &
b11101 0
b11101 -
0%
#2275000
1%
#2280000
b11111111111111111111111100110101 '
b11111111111111111111111100110101 1
b11110 &
b11110 0
b11110 -
0%
#2285000
1%
#2290000
b11111111111111111111110100101111 '
b11111111111111111111110100101111 1
b11111 &
b11111 0
b11111 -
0%
#2295000
1%
#2300000
b1010010001 '
b1010010001 1
b100000 &
b100000 0
b100000 -
0%
#2305000
1%
#2310000
b1110111100 '
b1110111100 1
b100001 &
b100001 0
b100001 -
0%
#2315000
1%
#2320000
b11111111111111111111110100101000 '
b11111111111111111111110100101000 1
b100010 &
b100010 0
b100010 -
0%
#2325000
1%
#2330000
b11011010 '
b11011010 1
b100011 &
b100011 0
b100011 -
0%
#2335000
1%
#2340000
b1010100011 '
b1010100011 1
b100100 &
b100100 0
b100100 -
0%
#2345000
1%
#2350000
b1110 '
b1110 1
b100101 &
b100101 0
b100101 -
0%
#2355000
1%
#2360000
b1110100 '
b1110100 1
b100110 &
b100110 0
b100110 -
0%
#2365000
1%
#2370000
b11111111111111111111111010100010 '
b11111111111111111111111010100010 1
b100111 &
b100111 0
b100111 -
0%
#2375000
1%
#2380000
b11111111111111111111111000101101 '
b11111111111111111111111000101101 1
b101000 &
b101000 0
b101000 -
0%
#2385000
1%
#2390000
b11111111111111111111110011010011 '
b11111111111111111111110011010011 1
b101001 &
b101001 0
b101001 -
0%
#2395000
1%
#2400000
b1000100110 '
b1000100110 1
b101010 &
b101010 0
b101010 -
0%
#2405000
1%
#2410000
b110 '
b110 1
b101011 &
b101011 0
b101011 -
0%
#2415000
1%
#2420000
b11111111111111111111111111110111 '
b11111111111111111111111111110111 1
b101100 &
b101100 0
b101100 -
0%
#2425000
1%
#2430000
b11111111111111111111110000101010 '
b11111111111111111111110000101010 1
b101101 &
b101101 0
b101101 -
0%
#2435000
1%
#2440000
b1010110110 '
b1010110110 1
b101110 &
b101110 0
b101110 -
0%
#2445000
1%
#2450000
0(
b101111 -
0%
#2455000
1%
#2460000
1+
0%
#2465000
0"
b1 6
b1 2
1%
#2470000
0+
0%
#2475000
b10 6
b0 3
b1000011101 4
1%
#2480000
0%
#2485000
b10 2
b1 3
b1000101001 4
1%
#2490000
0%
#2495000
b11 2
1%
#2500000
0%
#2505000
b100 2
1%
#2510000
0%
#2515000
b101 2
b100 3
b1011011101 4
1%
#2520000
0%
#2525000
b110 2
1%
#2530000
0%
#2535000
b111 2
1%
#2540000
0%
#2545000
b1000 2
1%
#2550000
0%
#2555000
b1001 2
1%
#2560000
0%
#2565000
b1010 2
b1001 3
b1100101010 4
1%
#2570000
0%
#2575000
b1011 2
1%
#2580000
0%
#2585000
b1100 2
1%
#2590000
0%
#2595000
b1101 2
1%
#2600000
0%
#2605000
b1110 2
1%
#2610000
0%
#2615000
b1111 2
b1110 3
b1100111010 4
1%
#2620000
0%
#2625000
b10000 2
1%
#2630000
0%
#2635000
b10001 2
1%
#2640000
0%
#2645000
b10010 2
1%
#2650000
0%
#2655000
b10011 2
1%
#2660000
0%
#2665000
b10100 2
1%
#2670000
0%
#2675000
b10101 2
1%
#2680000
0%
#2685000
b10110 2
1%
#2690000
0%
#2695000
b10111 2
1%
#2700000
0%
#2705000
b11000 2
1%
#2710000
0%
#2715000
b11001 2
1%
#2720000
0%
#2725000
b11010 2
1%
#2730000
0%
#2735000
b11011 2
1%
#2740000
0%
#2745000
b11100 2
1%
#2750000
0%
#2755000
b11101 2
1%
#2760000
0%
#2765000
b11110 2
1%
#2770000
0%
#2775000
b11111 2
1%
#2780000
0%
#2785000
b100000 2
1%
#2790000
0%
#2795000
b100001 2
1%
#2800000
0%
#2805000
b100010 2
b100001 3
b1110111100 4
1%
#2810000
0%
#2815000
b100011 2
1%
#2820000
0%
#2825000
b100100 2
1%
#2830000
0%
#2835000
b100101 2
1%
#2840000
0%
#2845000
b100110 2
1%
#2850000
0%
#2855000
b100111 2
1%
#2860000
0%
#2865000
b101000 2
1%
#2870000
0%
#2875000
b101001 2
1%
#2880000
0%
#2885000
b101010 2
1%
#2890000
0%
#2895000
b101011 2
1%
#2900000
0%
#2905000
b101100 2
1%
#2910000
0%
#2915000
b101101 2
1%
#2920000
0%
#2925000
b101110 2
1%
#2930000
0%
#2935000
1"
b0 6
1$
1!
b100001 #
b100001 5
1%
#2940000
b101100 .
b1110100000 )
b101111 -
b11 /
0%
#2945000
0!
0$
1%
#2950000
b11111111111111111111110100111000 '
b11111111111111111111110100111000 1
b0 &
b0 0
1(
b0 -
0%
#2955000
1%
#2960000
b1010011001 '
b1010011001 1
b1 &
b1 0
b1 -
0%
#2965000
1%
#2970000
b11111111111111111111111010010000 '
b11111111111111111111111010010000 1
b10 &
b10 0
b10 -
0%
#2975000
1%
#2980000
b11001100 '
b11001100 1
b11 &
b11 0
b11 -
0%
#2985000
1%
#2990000
b1101010011 '
b1101010011 1
b100 &
b100 0
b100 -
0%
#2995000
1%
#3000000
b11111111111111111111111101001100 '
b11111111111111111111111101001100 1
b101 &
b101 0
b101 -
0%
#3005000
1%
#3010000
b11111111111111111111111100000001 '
b11111111111111111111111100000001 1
b110 &
b110 0
b110 -
0%
#3015000
1%
#3020000
b111000011 '
b111000011 1
b111 &
b111 0
b111 -
0%
#3025000
1%
#3030000
b11111111111111111111111000110101 '
b11111111111111111111111000110101 1
b1000 &
b1000 0
b1000 -
0%
#3035000
1%
#3040000
b1011011001 '
b1011011001 1
b1001 &
b1001 0
b1001 -
0%
#3045000
1%
#3050000
b11111111111111111111111100001101 '
b11111111111111111111111100001101 1
b1010 &
b1010 0
b1010 -
0%
#3055000
1%
#3060000
b11111111111111111111110001001110 '
b11111111111111111111110001001110 1
b1011 &
b1011 0
b1011 -
0%
#3065000
1%
#3070000
b101001010 '
b101001010 1
b1100 &
b1100 0
b1100 -
0%
#3075000
1%
#3080000
b1010101110 '
b1010101110 1
b1101 &
b1101 0
b1101 -
0%
#3085000
1%
#3090000
b1101010101 '
b1101010101 1
b1110 &
b1110 0
b1110 -
0%
#3095000
1%
#3100000
b11111111111111111111110110011110 '
b11111111111111111111110110011110 1
b1111 &
b1111 0
b1111 -
0%
#3105000
1%
