rtl/fc2.v
`timescale 1ns / 1ps
// =============================================================
// FC2 : Lop ket noi day du 120 -> 84, kem quant + ReLU + clamp
// =============================================================
module fc2 (
    input  wire        clk,
    input  wire        rst_n,

    input  wire        start,
    output wire        ready,
    output reg         done,

    input  wire        in_wr_en,
    input  wire [6:0]  in_wr_addr,
    input  wire signed [7:0] in_wr_data,

    input  wire [6:0]  out_rd_addr,
    output wire signed [7:0]  out_rd_data
);

    reg signed [7:0]  f2_kernel [0:10079]; // 84 * 120
    reg signed [31:0] f2_bias   [0:83];
    reg signed [31:0] f2_mult   [0:83];
    reg [7:0]         f2_shift  [0:83];

    initial begin
        $readmemh("weights_hex/fc2_kernel.hex",     f2_kernel);
        $readmemh("weights_hex/fc2_bias.hex",       f2_bias);
        $readmemh("weights_hex/fc2_multiplier.hex", f2_mult);
        $readmemh("weights_hex/fc2_shift.hex",      f2_shift);
    end

    reg signed [7:0] fc1_out [0:119];
    reg signed [7:0] fc2_out [0:83];

    always @(posedge clk) begin
        if (in_wr_en) fc1_out[in_wr_addr] <= in_wr_data;
    end
    assign out_rd_data = fc2_out[out_rd_addr];

    localparam IDLE = 0, INIT = 1, MAC = 2, QUANT = 3;
    reg [2:0] state;

    reg [15:0] c, kc;
    reg signed [31:0] acc;
    reg signed [63:0] prod;

    assign ready = (state == IDLE);

    always @(posedge clk or negedge rst_n) begin
        if (!rst_n) begin
            state <= IDLE;
            done  <= 0;
        end else begin
            done <= 0;
            case (state)
                IDLE: begin
                    if (start) begin
                        c <= 0;
                        state <= INIT;
                    end
                end

                INIT: begin
                    acc <= f2_bias[c];
                    kc <= 0;
                    state <= MAC;
                end

                MAC: begin
                    acc <= acc + fc1_out[kc] * f2_kernel[c*120 + kc];
                    if (kc == 119) state <= QUANT;
                    else kc <= kc + 1;
                end

                QUANT: begin
                    prod = acc * f2_mult[c];
                    if (f2_shift[c] > 0) begin
                        prod = prod + (64'sd1 << (f2_shift[c] - 1));
                        acc = prod >>> f2_shift[c];
                    end else acc = prod;

                    if (acc > 127) acc = 127; else if (acc < -128) acc = -128;
                    if (acc < 0) acc = 0;
                    fc2_out[c] <= acc[7:0];

                    if (c == 83) begin
                        done  <= 1;
                        state <= IDLE;
                    end else begin
                        c <= c + 1;
                        state <= INIT;
                    end
                end
            endcase
        end
    end
endmodule

testbench/tb_fc2.v
`timescale 1ns / 1ps
// =============================================================
// TB_FC2 : Kiem tra doc lap module fc2 (120 -> 84)
// =============================================================
module tb_fc2;

    reg clk, rst_n, start;
    wire ready, done;

    reg        in_wr_en;
    reg [6:0]  in_wr_addr;
    reg signed [7:0] in_wr_data;

    reg  [6:0] out_rd_addr;
    wire signed [7:0] out_rd_data;

    fc2 dut (
        .clk(clk), .rst_n(rst_n),
        .start(start), .ready(ready), .done(done),
        .in_wr_en(in_wr_en), .in_wr_addr(in_wr_addr), .in_wr_data(in_wr_data),
        .out_rd_addr(out_rd_addr), .out_rd_data(out_rd_data)
    );

    initial clk = 0;
    always #5 clk = ~clk;

    // Xuat waveform ra file .vcd de xem bang GTKWave
    initial begin
        $dumpfile("fc2.vcd");
        $dumpvars(0, tb_fc2);
    end

    reg signed [7:0]  ref_kernel [0:10079];
    reg signed [31:0] ref_bias   [0:83];
    reg signed [31:0] ref_mult   [0:83];
    reg [7:0]         ref_shift  [0:83];

    reg signed [7:0] ref_in  [0:119];
    reg signed [7:0] ref_out [0:83];

    integer c, kc, i, errors;
    reg signed [31:0] acc;
    reg signed [63:0] prod;

    task compute_reference;
        begin
            for (c = 0; c < 84; c = c + 1) begin
                acc = ref_bias[c];
                for (kc = 0; kc < 120; kc = kc + 1)
                    acc = acc + ref_in[kc] * ref_kernel[c*120 + kc];

                prod = acc * ref_mult[c];
                if (ref_shift[c] > 0) begin
                    prod = prod + (64'sd1 << (ref_shift[c]-1));
                    acc  = prod >>> ref_shift[c];
                end else acc = prod;

                if (acc > 127) acc = 127; else if (acc < -128) acc = -128;
                if (acc < 0) acc = 0;

                ref_out[c] = acc[7:0];
            end
        end
    endtask

    initial begin
        $readmemh("weights_hex/fc2_kernel.hex",     ref_kernel);
        $readmemh("weights_hex/fc2_bias.hex",       ref_bias);
        $readmemh("weights_hex/fc2_multiplier.hex", ref_mult);
        $readmemh("weights_hex/fc2_shift.hex",      ref_shift);

        rst_n = 0; start = 0; in_wr_en = 0; in_wr_addr = 0; in_wr_data = 0;
        out_rd_addr = 0; errors = 0;

        repeat (3) @(posedge clk);
        @(negedge clk); rst_n = 1;

        for (i = 0; i < 120; i = i + 1)
            ref_in[i] = $random;

        compute_reference;

        @(negedge clk);
        for (i = 0; i < 120; i = i + 1) begin
            in_wr_en   = 1;
            in_wr_addr = i[6:0];
            in_wr_data = ref_in[i];
            @(negedge clk);
        end
        in_wr_en = 0;

        wait (ready);
        @(negedge clk); start = 1;
        @(negedge clk); start = 0;

        wait (done);
        @(negedge clk);

        for (i = 0; i < 84; i = i + 1) begin
            out_rd_addr = i[6:0];
            #1;
            if (out_rd_data !== ref_out[i]) begin
                errors = errors + 1;
                if (errors <= 10)
                    $display("[SAI] idx=%0d rtl=%0d ref=%0d", i, out_rd_data, ref_out[i]);
            end
        end

        if (errors == 0)
            $display("\n[PASS] fc2: tat ca 84 gia tri dau ra khop voi mo hinh tham chieu.\n");
        else
            $display("\n[FAIL] fc2: %0d / 84 gia tri sai khac.\n", errors);

        #20 $finish;
    end

    initial begin
        #500000;
        $display("[WATCHDOG] tb_fc2 qua thoi gian cho!");
        $finish;
    end
endmodule

results/fc2.vcd
$date
	Thu Jul 23 23:57:23 2026
$end
$version
	Icarus Verilog
$end
$timescale
	1ps
$end
$scope module tb_fc2 $end
$var wire 1 ! ready $end
$var wire 8 " out_rd_data [7:0] $end
$var wire 1 # done $end
$var reg 32 $ acc [31:0] $end
$var reg 1 % clk $end
$var reg 7 & in_wr_addr [6:0] $end
$var reg 8 ' in_wr_data [7:0] $end
$var reg 1 ( in_wr_en $end
$var reg 7 ) out_rd_addr [6:0] $end
$var reg 64 * prod [63:0] $end
$var reg 1 + rst_n $end
$var reg 1 , start $end
$var integer 32 - c [31:0] $end
$var integer 32 . errors [31:0] $end
$var integer 32 / i [31:0] $end
$var integer 32 0 kc [31:0] $end
$scope module dut $end
$var wire 1 % clk $end
$var wire 7 1 in_wr_addr [6:0] $end
$var wire 8 2 in_wr_data [7:0] $end
$var wire 1 ( in_wr_en $end
$var wire 7 3 out_rd_addr [6:0] $end
$var wire 8 4 out_rd_data [7:0] $end
$var wire 1 + rst_n $end
$var wire 1 , start $end
$var wire 1 ! ready $end
$var reg 32 5 acc [31:0] $end
$var reg 16 6 c [15:0] $end
$var reg 1 # done $end
$var reg 16 7 kc [15:0] $end
$var reg 64 8 prod [63:0] $end
$var reg 3 9 state [2:0] $end
$upscope $end
$scope task compute_reference $end
$upscope $end
$upscope $end
$enddefinitions $end
#0
$dumpvars
b0 9
bx 8
bx 7
bx 6
bx 5
bx 4
b0 3
b0 2
b0 1
bx 0
bx /
b0 .
bx -
0,
0+
bx *
b0 )
0(
b0 '
b0 &
0%
bx $
0#
bx "
1!
$end
#5000
1%
#10000
0%
#15000
1%
#20000
0%
#25000
1%
#30000
b1111111111111111111111111111111111100000110000010011100111101010 *
b1111000 0
b0 $
b1010100 -
b1111000 /
1+
0%
#35000
1%
#40000
b100100 '
b100100 2
1(
b0 /
0%
#45000
1%
#50000
b10000001 '
b10000001 2
b1 &
b1 1
b1 /
0%
#55000
1%
#60000
b1001 '
b1001 2
b10 &
b10 1
b10 /
0%
#65000
1%
#70000
b1100011 '
b1100011 2
b11 &
b11 1
b11 /
0%
#75000
1%
#80000
b1101 '
b1101 2
b100 &
b100 1
b100 /
0%
#85000
1%
#90000
b10001101 '
b10001101 2
b101 &
b101 1
b101 /
0%
#95000
1%
#100000
b1100101 '
b1100101 2
b110 &
b110 1
b110 /
0%
#105000
1%
#110000
b10010 '
b10010 2
b111 &
b111 1
b111 /
0%
#115000
1%
#120000
b1 '
b1 2
b1000 &
b1000 1
b1000 /
0%
#125000
1%
#130000
b1101 '
b1101 2
b1001 &
b1001 1
b1001 /
0%
#135000
1%
#140000
b1110110 '
b1110110 2
b1010 &
b1010 1
b1010 /
0%
#145000
1%
#150000
b111101 '
b111101 2
b1011 &
b1011 1
b1011 /
0%
#155000
1%
#160000
b11101101 '
b11101101 2
b1100 &
b1100 1
b1100 /
0%
#165000
1%
#170000
b10001100 '
b10001100 2
b1101 &
b1101 1
b1101 /
0%
#175000
1%
#180000
b11111001 '
b11111001 2
b1110 &
b1110 1
b1110 /
0%
#185000
1%
#190000
b11000110 '
b11000110 2
b1111 &
b1111 1
b1111 /
0%
#195000
1%
#200000
b11000101 '
b11000101 2
b10000 &
b10000 1
b10000 /
0%
#205000
1%
#210000
b10101010 '
b10101010 2
b10001 &
b10001 1
b10001 /
0%
#215000
1%
#220000
b11100101 '
b11100101 2
b10010 &
b10010 1
b10010 /
0%
#225000
1%
#230000
b1110111 '
b1110111 2
b10011 &
b10011 1
b10011 /
0%
#235000
1%
#240000
b10010 '
b10010 2
b10100 &
b10100 1
b10100 /
0%
#245000
1%
#250000
b10001111 '
b10001111 2
b10101 &
b10101 1
b10101 /
0%
#255000
1%
#260000
b11110010 '
b11110010 2
b10110 &
b10110 1
b10110 /
0%
#265000
1%
#270000
b11001110 '
b11001110 2
b10111 &
b10111 1
b10111 /
0%
#275000
1%
#280000
b11101000 '
b11101000 2
b11000 &
b11000 1
b11000 /
0%
#285000
1%
#290000
b11000101 '
b11000101 2
b11001 &
b11001 1
b11001 /
0%
#295000
1%
#300000
b1011100 '
b1011100 2
b11010 &
b11010 1
b11010 /
0%
#305000
1%
#310000
b10111101 '
b10111101 2
b11011 &
b11011 1
b11011 /
0%
#315000
1%
#320000
b101101 '
b101101 2
b11100 &
b11100 1
b11100 /
0%
#325000
1%
#330000
b1100101 '
b1100101 2
b11101 &
b11101 1
b11101 /
0%
#335000
1%
#340000
b1100011 '
b1100011 2
b11110 &
b11110 1
b11110 /
0%
#345000
1%
#350000
b1010 '
b1010 2
b11111 &
b11111 1
b11111 /
0%
#355000
1%
#360000
b10000000 '
b10000000 2
b100000 &
b100000 1
b100000 /
0%
#365000
1%
#370000
b100000 '
b100000 2
b100001 &
b100001 1
b100001 /
0%
#375000
1%
#380000
b10101010 '
b10101010 2
b100010 &
b100010 1
b100010 /
0%
#385000
1%
#390000
b10011101 '
b10011101 2
b100011 &
b100011 1
b100011 /
0%
#395000
1%
#400000
b10010110 '
b10010110 2
b100100 &
b100100 1
b100100 /
0%
#405000
1%
#410000
b10011 '
b10011 2
b100101 &
b100101 1
b100101 /
0%
#415000
1%
#420000
b1101 '
b1101 2
b100110 &
b100110 1
b100110 /
0%
#425000
1%
#430000
b1010011 '
b1010011 2
b100111 &
b100111 1
b100111 /
0%
#435000
1%
#440000
b1101011 '
b1101011 2
b101000 &
b101000 1
b101000 /
0%
#445000
1%
#450000
b11010101 '
b11010101 2
b101001 &
b101001 1
b101001 /
0%
#455000
1%
#460000
b10 '
b10 2
b101010 &
b101010 1
b101010 /
0%
#465000
1%
#470000
b10101110 '
b10101110 2
b101011 &
b101011 1
b101011 /
0%
#475000
1%
#480000
b11101 '
b11101 2
b101100 &
b101100 1
b101100 /
0%
#485000
1%
#490000
b11001111 '
b11001111 2
b101101 &
b101101 1
b101101 /
0%
#495000
1%
#500000
b100011 '
b100011 2
b101110 &
b101110 1
b101110 /
0%
#505000
1%
#510000
b1010 '
b1010 2
b101111 &
b101111 1
b101111 /
0%
#515000
1%
#520000
b11001010 '
b11001010 2
b110000 &
b110000 1
b110000 /
0%
#525000
1%
#530000
b111100 '
b111100 2
b110001 &
b110001 1
b110001 /
0%
#535000
1%
#540000
b11110010 '
b11110010 2
b110010 &
b110010 1
b110010 /
0%
#545000
1%
#550000
b10001010 '
b10001010 2
b110011 &
b110011 1
b110011 /
0%
#555000
1%
#560000
b1000001 '
b1000001 2
b110100 &
b110100 1
b110100 /
0%
#565000
1%
#570000
b11011000 '
b11011000 2
b110101 &
b110101 1
b110101 /
0%
#575000
1%
#580000
b1111000 '
b1111000 2
b110110 &
b110110 1
b110110 /
0%
#585000
1%
#590000
b10001001 '
b10001001 2
b110111 &
b110111 1
b110111 /
0%
#595000
1%
#600000
b11101011 '
b11101011 2
b111000 &
b111000 1
b111000 /
0%
#605000
1%
#610000
b10110110 '
b10110110 2
b111001 &
b111001 1
b111001 /
0%
#615000
1%
#620000
b11000110 '
b11000110 2
b111010 &
b111010 1
b111010 /
0%
#625000
1%
#630000
b10101110 '
b10101110 2
b111011 &
b111011 1
b111011 /
0%
#635000
1%
#640000
b10111100 '
b10111100 2
b111100 &
b111100 1
b111100 /
0%
#645000
1%
#650000
b101010 '
b101010 2
b111101 &
b111101 1
b111101 /
0%
#655000
1%
#660000
b1011 '
b1011 2
b111110 &
b111110 1
b111110 /
0%
#665000
1%
#670000
b1110001 '
b1110001 2
b111111 &
b111111 1
b111111 /
0%
#675000
1%
#680000
b10000101 '
b10000101 2
b1000000 &
b1000000 1
b1000000 /
0%
#685000
1%
#690000
b1001111 '
b1001111 2
b1000001 &
b1000001 1
b1000001 /
0%
#695000
1%
#700000
b111011 '
b111011 2
b1000010 &
b1000010 1
b1000010 /
0%
#705000
1%
#710000
b111010 '
b111010 2
b1000011 &
b1000011 1
b1000011 /
0%
#715000
1%
#720000
b1111110 '
b1111110 2
b1000100 &
b1000100 1
b1000100 /
0%
#725000
1%
#730000
b10101 '
b10101 2
b1000101 &
b1000101 1
b1000101 /
0%
#735000
1%
#740000
b11110001 '
b11110001 2
b1000110 &
b1000110 1
b1000110 /
0%
#745000
1%
#750000
b11011001 '
b11011001 2
b1000111 &
b1000111 1
b1000111 /
0%
#755000
1%
#760000
b1100010 '
b1100010 2
b1001000 &
b1001000 1
b1001000 /
0%
#765000
1%
#770000
b1001100 '
b1001100 2
b1001001 &
b1001001 1
b1001001 /
0%
#775000
1%
#780000
b10011111 '
b10011111 2
b1001010 &
b1001010 1
b1001010 /
0%
#785000
1%
#790000
b10001111 '
b10001111 2
b1001011 &
b1001011 1
b1001011 /
0%
#795000
1%
#800000
b11111000 '
b11111000 2
b1001100 &
b1001100 1
b1001100 /
0%
#805000
1%
#810000
b10110111 '
b10110111 2
b1001101 &
b1001101 1
b1001101 /
0%
#815000
1%
#820000
b10011111 '
b10011111 2
b1001110 &
b1001110 1
b1001110 /
0%
#825000
1%
#830000
b1011100 '
b1011100 2
b1001111 &
b1001111 1
b1001111 /
0%
#835000
1%
#840000
b1011011 '
b1011011 2
b1010000 &
b1010000 1
b1010000 /
0%
#845000
1%
#850000
b10001001 '
b10001001 2
b1010001 &
b1010001 1
b1010001 /
0%
#855000
1%
#860000
b1001001 '
b1001001 2
b1010010 &
b1010010 1
b1010010 /
0%
#865000
1%
#870000
b11010000 '
b11010000 2
b1010011 &
b1010011 1
b1010011 /
0%
#875000
1%
#880000
b11010111 '
b11010111 2
b1010100 &
b1010100 1
b1010100 /
0%
#885000
1%
#890000
b1010001 '
b1010001 2
b1010101 &
b1010101 1
b1010101 /
0%
#895000
1%
#900000
b10010110 '
b10010110 2
b1010110 &
b1010110 1
b1010110 /
0%
#905000
1%
#910000
b1100 '
b1100 2
b1010111 &
b1010111 1
b1010111 /
0%
#915000
1%
#920000
b11000010 '
b11000010 2
b1011000 &
b1011000 1
b1011000 /
0%
#925000
1%
#930000
b11001000 '
b11001000 2
b1011001 &
b1011001 1
b1011001 /
0%
#935000
1%
#940000
b1110111 '
b1110111 2
b1011010 &
b1011010 1
b1011010 /
0%
#945000
1%
#950000
b111101 '
b111101 2
b1011011 &
b1011011 1
b1011011 /
0%
#955000
1%
#960000
b10010 '
b10010 2
b1011100 &
b1011100 1
b1011100 /
0%
#965000
1%
#970000
b1111110 '
b1111110 2
b1011101 &
b1011101 1
b1011101 /
0%
#975000
1%
#980000
b1101101 '
b1101101 2
b1011110 &
b1011110 1
b1011110 /
0%
#985000
1%
#990000
b111001 '
b111001 2
b1011111 &
b1011111 1
b1011111 /
0%
#995000
1%
#1000000
b11111 '
b11111 2
b1100000 &
b1100000 1
b1100000 /
0%
#1005000
1%
#1010000
b11010011 '
b11010011 2
b1100001 &
b1100001 1
b1100001 /
0%
#1015000
1%
#1020000
b10000101 '
b10000101 2
b1100010 &
b1100010 1
b1100010 /
0%
#1025000
1%
#1030000
b1111000 '
b1111000 2
b1100011 &
b1100011 1
b1100011 /
0%
#1035000
1%
#1040000
b1011011 '
b1011011 2
b1100100 &
b1100100 1
b1100100 /
0%
#1045000
1%
#1050000
b1001001 '
b1001001 2
b1100101 &
b1100101 1
b1100101 /
0%
#1055000
1%
#1060000
b111111 '
b111111 2
b1100110 &
b1100110 1
b1100110 /
0%
#1065000
1%
#1070000
b101010 '
b101010 2
b1100111 &
b1100111 1
b1100111 /
0%
#1075000
1%
#1080000
b1011000 '
b1011000 2
b1101000 &
b1101000 1
b1101000 /
0%
#1085000
1%
#1090000
b10000110 '
b10000110 2
b1101001 &
b1101001 1
b1101001 /
0%
#1095000
1%
#1100000
b10001110 '
b10001110 2
b1101010 &
b1101010 1
b1101010 /
0%
#1105000
1%
#1110000
b10011100 '
b10011100 2
b1101011 &
b1101011 1
b1101011 /
0%
#1115000
1%
#1120000
b11111010 '
b11111010 2
b1101100 &
b1101100 1
b1101100 /
0%
#1125000
1%
#1130000
b100110 '
b100110 2
b1101101 &
b1101101 1
b1101101 /
0%
#1135000
1%
#1140000
b1110011 '
b1110011 2
b1101110 &
b1101110 1
b1101110 /
0%
#1145000
1%
#1150000
b10100011 '
b10100011 2
b1101111 &
b1101111 1
b1101111 /
0%
#1155000
1%
#1160000
b101111 '
b101111 2
b1110000 &
b1110000 1
b1110000 /
0%
#1165000
1%
#1170000
b10110011 '
b10110011 2
b1110001 &
b1110001 1
b1110001 /
0%
#1175000
1%
#1180000
b1011111 '
b1011111 2
b1110010 &
b1110010 1
b1110010 /
0%
#1185000
1%
#1190000
b1000100 '
b1000100 2
b1110011 &
b1110011 1
b1110011 /
0%
#1195000
1%
#1200000
b11110111 '
b11110111 2
b1110100 &
b1110100 1
b1110100 /
0%
#1205000
1%
#1210000
b11001011 '
b11001011 2
b1110101 &
b1110101 1
b1110101 /
0%
#1215000
1%
#1220000
b11100110 '
b11100110 2
b1110110 &
b1110110 1
b1110110 /
0%
#1225000
1%
#1230000
b1011010 '
b1011010 2
b1110111 &
b1110111 1
b1110111 /
0%
#1235000
1%
#1240000
0(
b1111000 /
0%
#1245000
1%
#1250000
1,
0%
#1255000
0!
b1 9
b0 6
1%
#1260000
0,
0%
#1265000
b10 9
b0 7
b100001 5
1%
#1270000
0%
#1275000
b1 7
b110000111001 5
1%
#1280000
0%
#1285000
b10 7
b10000110001110 5
1%
#1290000
0%
#1295000
b11 7
b10001000001100 5
1%
#1300000
0%
#1305000
b100 7
b10100111001000 5
1%
#1310000
0%
#1315000
b101 7
b10101111110111 5
1%
#1320000
0%
#1325000
b110 7
b11111101001000 5
1%
#1330000
0%
#1335000
b111 7
b100001001110000 5
1%
#1340000
0%
#1345000
b1000 7
b100000000011110 5
1%
#1350000
0%
#1355000
b1001 7
b11111111111101 5
1%
#1360000
0%
#1365000
b1010 7
b100001110111111 5
1%
#1370000
0%
#1375000
b1011 7
b100100110111101 5
1%
#1380000
0%
#1385000
b1100 7
b100110001011100 5
1%
#1390000
0%
#1395000
b1101 7
b100100111111100 5
1%
#1400000
0%
#1405000
b1110 7
b110001011101000 5
1%
#1410000
0%
#1415000
b1111 7
b110010000111111 5
1%
#1420000
0%
#1425000
b10000 7
b110011010000011 5
1%
#1430000
0%
#1435000
b10001 7
b110000001001010 5
1%
#1440000
0%
#1445000
b10010 7
b110010101010100 5
1%
#1450000
0%
#1455000
b10011 7
b101101101101010 5
1%
#1460000
0%
#1465000
b10100 7
b101011011000100 5
1%
#1470000
0%
#1475000
b10101 7
b101011110001010 5
1%
#1480000
0%
#1485000
b10110 7
b11101110111011 5
1%
#1490000
0%
#1495000
b10111 7
b11101101011001 5
1%
#1500000
0%
#1505000
b11000 7
b11111110100101 5
1%
#1510000
0%
#1515000
b11001 7
b100000110110101 5
1%
#1520000
0%
#1525000
b11010 7
b11011001101010 5
1%
#1530000
0%
#1535000
b11011 7
b100010110000010 5
1%
#1540000
0%
#1545000
b11100 7
b101000111001111 5
1%
#1550000
0%
#1555000
b11101 7
b100001010000100 5
1%
#1560000
0%
#1565000
b11110 7
b110000011100101 5
1%
#1570000
0%
#1575000
b11111 7
b111001111011000 5
1%
#1580000
0%
#1585000
b100000 7
b111010101000000 5
1%
#1590000
0%
#1595000
b100001 7
b1000101101000000 5
1%
#1600000
0%
#1605000
b100010 7
b1000111001000000 5
1%
#1610000
0%
#1615000
b100011 7
b111100000010100 5
1%
#1620000
0%
#1625000
b100100 7
b110111111110101 5
1%
#1630000
0%
#1635000
b100101 7
b111111101000111 5
1%
#1640000
0%
#1645000
b100110 7
b1000000100100010 5
1%
#1650000
0%
#1655000
b100111 7
b1000000101010110 5
1%
#1660000
0%
#1665000
b101000 7
b1000011011011001 5
1%
#1670000
0%
#1675000
b101001 7
b1001111110000010 5
1%
#1680000
0%
#1685000
b101010 7
b1001101001001101 5
1%
#1690000
0%
#1695000
b101011 7
b1001100111100101 5
1%
#1700000
0%
#1705000
b101100 7
b1001101111010001 5
1%
#1710000
0%
#1715000
b101101 7
b1001011001000100 5
1%
#1720000
0%
#1725000
b101110 7
b1000100100001111 5
1%
#1730000
0%
#1735000
b101111 7
b1000010100111011 5
1%
#1740000
0%
#1745000
b110000 7
b1000010100001001 5
1%
#1750000
0%
#1755000
b110001 7
b1000001100100011 5
1%
#1760000
0%
#1765000
b110010 7
b111100100001111 5
1%
#1770000
0%
#1775000
b110011 7
b111011110100011 5
1%
#1780000
0%
#1785000
b110100 7
b1000001010110011 5
1%
#1790000
0%
#1795000
b110101 7
b111100110001111 5
1%
#1800000
0%
#1805000
b110110 7
b111111011011111 5
1%
#1810000
0%
#1815000
b110111 7
b1000010101101111 5
1%
#1820000
0%
#1825000
b111000 7
b111110100010001 5
1%
#1830000
0%
#1835000
b111001 7
b111110000111111 5
1%
#1840000
0%
#1845000
b111010 7
b111111011011001 5
1%
#1850000
0%
#1855000
b111011 7
b1000000010101001 5
1%
#1860000
0%
#1865000
b111100 7
b110110100011111 5
1%
#1870000
0%
#1875000
b111101 7
b1000000011000111 5
1%
#1880000
0%
#1885000
b111110 7
b111110001011001 5
1%
#1890000
0%
#1895000
b111111 7
b111110100110101 5
1%
#1900000
0%
#1905000
b1000000 7
b1000110110001010 5
1%
#1910000
0%
#1915000
b1000001 7
b1011101000111001 5
1%
#1920000
0%
#1925000
b1000010 7
b1100100111110110 5
1%
#1930000
0%
#1935000
b1000011 7
b1010110010110001 5
1%
#1940000
0%
#1945000
b1000100 7
b1010100100010001 5
1%
#1950000
0%
#1955000
b1000101 7
b1000000110110001 5
1%
#1960000
0%
#1965000
b1000110 7
b1000000110000111 5
1%
#1970000
0%
#1975000
b1000111 7
b1000000111100001 5
1%
#1980000
0%
#1985000
b1001000 7
b1000100010111100 5
1%
#1990000
0%
#1995000
b1001001 7
b1010001011000100 5
1%
#2000000
0%
#2005000
b1001010 7
b1010110011011100 5
1%
#2010000
0%
#2015000
b1001011 7
b1100000011110001 5
1%
#2020000
0%
#2025000
b1001100 7
b1101000101000110 5
1%
#2030000
0%
#2035000
b1001101 7
b1101001011111110 5
1%
#2040000
0%
#2045000
b1001110 7
b1101010011111101 5
1%
#2050000
0%
#2055000
b1001111 7
b1100001111110000 5
1%
#2060000
0%
#2065000
b1010000 7
b1100110010010000 5
1%
#2070000
0%
#2075000
b1010001 7
b1110110111111010 5
1%
#2080000
0%
#2085000
b1010010 7
b1111110001100011 5
1%
#2090000
0%
#2095000
b1010011 7
b1111100010101110 5
1%
#2100000
0%
#2105000
b1010100 7
b10000000001011110 5
1%
#2110000
0%
#2115000
b1010101 7
b1111011110111000 5
1%
#2120000
0%
#2125000
b1010110 7
b1110100111001100 5
1%
#2130000
0%
#2135000
b1010111 7
b1101100110100110 5
1%
#2140000
0%
#2145000
b1011000 7
b1101110110001010 5
1%
#2150000
0%
#2155000
b1011001 7
b1100100111101100 5
1%
#2160000
0%
#2165000
b1011010 7
b1100101011001100 5
1%
#2170000
0%
#2175000
b1011011 7
b1011010111100001 5
1%
#2180000
0%
#2185000
b1011100 7
b1011101111010110 5
1%
#2190000
0%
#2195000
b1011101 7
b1011101010100100 5
1%
#2200000
0%
#2205000
b1011110 7
b1100010011111010 5
1%
#2210000
0%
#2215000
b1011111 7
b1110001011001000 5
1%
#2220000
0%
#2225000
b1100000 7
b1110101100111110 5
1%
#2230000
0%
#2235000
b1100001 7
b1110111111011000 5
1%
#2240000
0%
#2245000
b1100010 7
b1110001111100100 5
1%
#2250000
0%
#2255000
b1100011 7
b1110100010110010 5
1%
#2260000
0%
#2265000
b1100100 7
b1111000000110010 5
1%
#2270000
0%
#2275000
b1100101 7
b1110000011101001 5
1%
#2280000
0%
#2285000
b1100110 7
b1100101110000110 5
1%
#2290000
0%
#2295000
b1100111 7
b1101110010000001 5
1%
#2300000
0%
#2305000
b1101000 7
b1101010110011101 5
1%
#2310000
0%
#2315000
b1101001 7
b1101100110111101 5
1%
#2320000
0%
#2325000
b1101010 7
b1100010100111111 5
1%
#2330000
0%
#2335000
b1101011 7
b1100000001011001 5
1%
#2340000
0%
#2345000
b1101100 7
b1010100110110001 5
1%
#2350000
0%
#2355000
b1101101 7
b1010101001110001 5
1%
#2360000
0%
#2365000
b1101110 7
b1011000101101011 5
1%
#2370000
0%
#2375000
b1101111 7
b1001011011101010 5
1%
#2380000
0%
#2385000
b1110000 7
b1001011110100100 5
1%
#2390000
0%
#2395000
b1110001 7
b1010011100010000 5
1%
#2400000
0%
#2405000
b1110010 7
b1010100010010001 5
1%
#2410000
0%
#2415000
b1110011 7
b1011010001110001 5
1%
#2420000
0%
#2425000
b1110100 7
b1011010000101101 5
1%
#2430000
0%
#2435000
b1110101 7
b1011001011010111 5
1%
#2440000
0%
#2445000
b1110110 7
b1100000101010101 5
1%
#2450000
0%
#2455000
b1110111 7
b1011101011010101 5
1%
#2460000
0%
#2465000
b11 9
b1011011001000011 5
1%
#2470000
0%
#2475000
b1 9
b1 6
b1001111 "
b1001111 4
b1001111 5
b1001111111111010011110001110010 8
1%
#2480000
0%
#2485000
b10 9
b0 7
b10001100 5
1%
#2490000
0%
#2495000
b1 7
b11111111111111111111101111101000 5
1%
#2500000
0%
#2505000
b10 7
b11111111111111111101111000100100 5
1%
#2510000
0%
#2515000
b11 7
b11111111111111111101101100000011 5
1%
#2520000
0%
#2525000
b100 7
b11111111111111111101100101110111 5
1%
#2530000
0%
#2535000
b101 7
b11111111111111111101010110001110 5
1%
#2540000
0%
#2545000
b110 7
b11111111111111111011100001011011 5
1%
#2550000
0%
#2555000
b111 7
b11111111111111111010101011110001 5
1%
#2560000
0%
#2565000
b1000 7
b11111111111111111010110101010101 5
1%
#2570000
0%
#2575000
b1001 7
b11111111111111111010110101101000 5
1%
#2580000
0%
#2585000
b1010 7
b11111111111111111010101011111000 5
1%
#2590000
0%
#2595000
b1011 7
b11111111111111111101001111111110 5
1%
#2600000
0%
#2605000
b1100 7
b11111111111111111110010011101001 5
1%
#2610000
0%
#2615000
b1101 7
b11111111111111111110100010110010 5
1%
#2620000
0%
#2625000
b1110 7
b11111111111111111110111100001010 5
1%
#2630000
0%
#2635000
b1111 7
b11111111111111111111000011100110 5
1%
#2640000
0%
#2645000
b10000 7
b11111111111111111110110010011000 5
1%
#2650000
0%
#2655000
b10001 7
b11111111111111111110100000110111 5
1%
#2660000
0%
#2665000
b10010 7
b11111111111111111110001000101011 5
1%
#2670000
0%
#2675000
b10011 7
b11111111111111111110010110100110 5
1%
#2680000
0%
#2685000
b10100 7
b11111111111111111110111001111011 5
1%
#2690000
0%
#2695000
b10101 7
b11111111111111111111010010111101 5
1%
#2700000
0%
#2705000
b10110 7
b111111011 5
1%
#2710000
0%
#2715000
b10111 7
b11111111111111111111111001101101 5
1%
#2720000
0%
#2725000
b11000 7
b11111111111111111111011100000001 5
1%
#2730000
0%
#2735000
b11001 7
b11111111111111111111100110111001 5
1%
#2740000
0%
#2745000
b11010 7
b11111111111111111110100001110000 5
1%
#2750000
0%
#2755000
b11011 7
b11111111111111111111110110100100 5
1%
#2760000
0%
#2765000
b11100 7
b1011100000 5
1%
#2770000
0%
#2775000
b11101 7
b11111111111111111111111100000010 5
1%
#2780000
0%
#2785000
b11110 7
b111111111001 5
1%
#2790000
0%
#2795000
b11111 7
b110011100001 5
1%
#2800000
0%
#2805000
b100000 7
b100011010001 5
1%
#2810000
0%
#2815000
b100001 7
b10001010001 5
1%
#2820000
0%
#2825000
b100010 7
b101001110001 5
1%
#2830000
0%
#2835000
b100011 7
b11111111111111111111011110100001 5
1%
#2840000
0%
#2845000
b100100 7
b11111111111111111111011000010101 5
1%
#2850000
0%
#2855000
b100101 7
b11111111111111111111000111110001 5
1%
#2860000
0%
#2865000
b100110 7
b11111111111111111110110001110011 5
1%
#2870000
0%
#2875000
b100111 7
b11111111111111111110111011110000 5
1%
#2880000
0%
#2885000
b101000 7
b11111111111111111101111010111010 5
1%
#2890000
0%
#2895000
b101001 7
b11111111111111111101001010011011 5
1%
#2900000
0%
#2905000
b101010 7
b11111111111111111101111000110010 5
1%
#2910000
0%
#2915000
b101011 7
b11111111111111111101110110011110 5
1%
#2920000
0%
#2925000
b101100 7
b11111111111111111100011000111100 5
1%
#2930000
0%
#2935000
b101101 7
b11111111111111111100000110110100 5
1%
#2940000
0%
