rtl/fc3.v
`timescale 1ns / 1ps
// =============================================================
// FC3 : Lop ket noi day du 84 -> 47 (lop logit dau ra)
// KHONG dung luong tu hoa (mult/shift) va KHONG dung ReLU
// =============================================================
module fc3 (
    input  wire        clk,
    input  wire        rst_n,

    input  wire        start,
    output wire        ready,
    output reg         done,

    input  wire        in_wr_en,
    input  wire [6:0]  in_wr_addr,
    input  wire signed [7:0] in_wr_data,

    // Dau ra la logit 32-bit, chua qua ReLU/quant
    input  wire [5:0]  out_rd_addr,
    output wire signed [31:0] out_rd_data
);

    reg signed [7:0]  f3_kernel [0:3947]; // 47 * 84
    reg signed [31:0] f3_bias   [0:46];

    initial begin
        $readmemh("weights_hex/fc3_kernel.hex", f3_kernel);
        $readmemh("weights_hex/fc3_bias.hex",   f3_bias);
    end

    reg signed [7:0]  fc2_out [0:83];
    reg signed [31:0] fc3_out [0:46];

    always @(posedge clk) begin
        if (in_wr_en) fc2_out[in_wr_addr] <= in_wr_data;
    end
    assign out_rd_data = fc3_out[out_rd_addr];

    localparam IDLE = 0, INIT = 1, MAC = 2, STORE = 3;
    reg [2:0] state;

    reg [15:0] c, kc;
    reg signed [31:0] acc;

    assign ready = (state == IDLE);

    always @(posedge clk or negedge rst_n) begin
        if (!rst_n) begin
            state <= IDLE;
            done  <= 0;
        end else begin
            done <= 0;
            case (state)
                IDLE: begin
                    if (start) begin
                        c <= 0;
                        state <= INIT;
                    end
                end

                INIT: begin
                    acc <= f3_bias[c];
                    kc <= 0;
                    state <= MAC;
                end

                MAC: begin
                    acc <= acc + fc2_out[kc] * f3_kernel[c*84 + kc];
                    if (kc == 83) state <= STORE;
                    else kc <= kc + 1;
                end

                STORE: begin
                    fc3_out[c] <= acc; // Khong luong tu hoa & khong ReLU
                    if (c == 46) begin
                        done  <= 1;
                        state <= IDLE;
                    end else begin
                        c <= c + 1;
                        state <= INIT;
                    end
                end
            endcase
        end
    end
endmodule

testbench/tb_fc3.v
`timescale 1ns / 1ps
// =============================================================
// TB_FC3 : Kiem tra doc lap module fc3 (84 -> 47, khong quant/ReLU)
// =============================================================
module tb_fc3;

    reg clk, rst_n, start;
    wire ready, done;

    reg        in_wr_en;
    reg [6:0]  in_wr_addr;
    reg signed [7:0] in_wr_data;

    reg  [5:0] out_rd_addr;
    wire signed [31:0] out_rd_data;

    fc3 dut (
        .clk(clk), .rst_n(rst_n),
        .start(start), .ready(ready), .done(done),
        .in_wr_en(in_wr_en), .in_wr_addr(in_wr_addr), .in_wr_data(in_wr_data),
        .out_rd_addr(out_rd_addr), .out_rd_data(out_rd_data)
    );

    initial clk = 0;
    always #5 clk = ~clk;

    // Xuat waveform ra file .vcd de xem bang GTKWave
    initial begin
        $dumpfile("fc3.vcd");
        $dumpvars(0, tb_fc3);
    end

    reg signed [7:0]  ref_kernel [0:3947];
    reg signed [31:0] ref_bias   [0:46];

    reg signed [7:0]  ref_in  [0:83];
    reg signed [31:0] ref_out [0:46];

    integer c, kc, i, errors;
    reg signed [31:0] acc;

    task compute_reference;
        begin
            for (c = 0; c < 47; c = c + 1) begin
                acc = ref_bias[c];
                for (kc = 0; kc < 84; kc = kc + 1)
                    acc = acc + ref_in[kc] * ref_kernel[c*84 + kc];
                ref_out[c] = acc;
            end
        end
    endtask

    initial begin
        $readmemh("weights_hex/fc3_kernel.hex", ref_kernel);
        $readmemh("weights_hex/fc3_bias.hex",   ref_bias);

        rst_n = 0; start = 0; in_wr_en = 0; in_wr_addr = 0; in_wr_data = 0;
        out_rd_addr = 0; errors = 0;

        repeat (3) @(posedge clk);
        @(negedge clk); rst_n = 1;

        for (i = 0; i < 84; i = i + 1)
            ref_in[i] = $random;

        compute_reference;

        @(negedge clk);
        for (i = 0; i < 84; i = i + 1) begin
            in_wr_en   = 1;
            in_wr_addr = i[6:0];
            in_wr_data = ref_in[i];
            @(negedge clk);
        end
        in_wr_en = 0;

        wait (ready);
        @(negedge clk); start = 1;
        @(negedge clk); start = 0;

        wait (done);
        @(negedge clk);

        for (i = 0; i < 47; i = i + 1) begin
            out_rd_addr = i[5:0];
            #1;
            if (out_rd_data !== ref_out[i]) begin
                errors = errors + 1;
                if (errors <= 10)
                    $display("[SAI] idx=%0d rtl=%0d ref=%0d", i, out_rd_data, ref_out[i]);
            end
        end

        if (errors == 0)
            $display("\n[PASS] fc3: tat ca 47 gia tri logit khop voi mo hinh tham chieu.\n");
        else
            $display("\n[FAIL] fc3: %0d / 47 gia tri sai khac.\n", errors);

        #20 $finish;
    end

    initial begin
        #500000;
        $display("[WATCHDOG] tb_fc3 qua thoi gian cho!");
        $finish;
    end
endmodule

results/fc3.vcd
$date
	Thu Jul 23 23:58:11 2026
$end
$version
	Icarus Verilog
$end
$timescale
	1ps
$end
$scope module tb_fc3 $end
$var wire 1 ! ready $end
$var wire 32 " out_rd_data [31:0] $end
$var wire 1 # done $end
$var reg 32 $ acc [31:0] $end
$var reg 1 % clk $end
$var reg 7 & in_wr_addr [6:0] $end
$var reg 8 ' in_wr_data [7:0] $end
$var reg 1 ( in_wr_en $end
$var reg 6 ) out_rd_addr [5:0] $end
$var reg 1 * rst_n $end
$var reg 1 + start $end
$var integer 32 , c [31:0] $end
$var integer 32 - errors [31:0] $end
$var integer 32 . i [31:0] $end
$var integer 32 / kc [31:0] $end
$scope module dut $end
$var wire 1 % clk $end
$var wire 7 0 in_wr_addr [6:0] $end
$var wire 8 1 in_wr_data [7:0] $end
$var wire 1 ( in_wr_en $end
$var wire 6 2 out_rd_addr [5:0] $end
$var wire 32 3 out_rd_data [31:0] $end
$var wire 1 * rst_n $end
$var wire 1 + start $end
$var wire 1 ! ready $end
$var reg 32 4 acc [31:0] $end
$var reg 16 5 c [15:0] $end
$var reg 1 # done $end
$var reg 16 6 kc [15:0] $end
$var reg 3 7 state [2:0] $end
$upscope $end
$scope task compute_reference $end
$upscope $end
$upscope $end
$enddefinitions $end
#0
$dumpvars
b0 7
bx 6
bx 5
bx 4
bx 3
b0 2
b0 1
b0 0
bx /
bx .
b0 -
bx ,
0+
0*
b0 )
0(
b0 '
b0 &
0%
bx $
0#
bx "
1!
$end
#5000
1%
#10000
0%
#15000
1%
#20000
0%
#25000
1%
#30000
b1010100 /
b11111111111111111110011001011110 $
b101111 ,
b1010100 .
1*
0%
#35000
1%
#40000
b100100 '
b100100 1
1(
b0 .
0%
#45000
1%
#50000
b10000001 '
b10000001 1
b1 &
b1 0
b1 .
0%
#55000
1%
#60000
b1001 '
b1001 1
b10 &
b10 0
b10 .
0%
#65000
1%
#70000
b1100011 '
b1100011 1
b11 &
b11 0
b11 .
0%
#75000
1%
#80000
b1101 '
b1101 1
b100 &
b100 0
b100 .
0%
#85000
1%
#90000
b10001101 '
b10001101 1
b101 &
b101 0
b101 .
0%
#95000
1%
#100000
b1100101 '
b1100101 1
b110 &
b110 0
b110 .
0%
#105000
1%
#110000
b10010 '
b10010 1
b111 &
b111 0
b111 .
0%
#115000
1%
#120000
b1 '
b1 1
b1000 &
b1000 0
b1000 .
0%
#125000
1%
#130000
b1101 '
b1101 1
b1001 &
b1001 0
b1001 .
0%
#135000
1%
#140000
b1110110 '
b1110110 1
b1010 &
b1010 0
b1010 .
0%
#145000
1%
#150000
b111101 '
b111101 1
b1011 &
b1011 0
b1011 .
0%
#155000
1%
#160000
b11101101 '
b11101101 1
b1100 &
b1100 0
b1100 .
0%
#165000
1%
#170000
b10001100 '
b10001100 1
b1101 &
b1101 0
b1101 .
0%
#175000
1%
#180000
b11111001 '
b11111001 1
b1110 &
b1110 0
b1110 .
0%
#185000
1%
#190000
b11000110 '
b11000110 1
b1111 &
b1111 0
b1111 .
0%
#195000
1%
#200000
b11000101 '
b11000101 1
b10000 &
b10000 0
b10000 .
0%
#205000
1%
#210000
b10101010 '
b10101010 1
b10001 &
b10001 0
b10001 .
0%
#215000
1%
#220000
b11100101 '
b11100101 1
b10010 &
b10010 0
b10010 .
0%
#225000
1%
#230000
b1110111 '
b1110111 1
b10011 &
b10011 0
b10011 .
0%
#235000
1%
#240000
b10010 '
b10010 1
b10100 &
b10100 0
b10100 .
0%
#245000
1%
#250000
b10001111 '
b10001111 1
b10101 &
b10101 0
b10101 .
0%
#255000
1%
#260000
b11110010 '
b11110010 1
b10110 &
b10110 0
b10110 .
0%
#265000
1%
#270000
b11001110 '
b11001110 1
b10111 &
b10111 0
b10111 .
0%
#275000
1%
#280000
b11101000 '
b11101000 1
b11000 &
b11000 0
b11000 .
0%
#285000
1%
#290000
b11000101 '
b11000101 1
b11001 &
b11001 0
b11001 .
0%
#295000
1%
#300000
b1011100 '
b1011100 1
b11010 &
b11010 0
b11010 .
0%
#305000
1%
#310000
b10111101 '
b10111101 1
b11011 &
b11011 0
b11011 .
0%
#315000
1%
#320000
b101101 '
b101101 1
b11100 &
b11100 0
b11100 .
0%
#325000
1%
#330000
b1100101 '
b1100101 1
b11101 &
b11101 0
b11101 .
0%
#335000
1%
#340000
b1100011 '
b1100011 1
b11110 &
b11110 0
b11110 .
0%
#345000
1%
#350000
b1010 '
b1010 1
b11111 &
b11111 0
b11111 .
0%
#355000
1%
#360000
b10000000 '
b10000000 1
b100000 &
b100000 0
b100000 .
0%
#365000
1%
#370000
b100000 '
b100000 1
b100001 &
b100001 0
b100001 .
0%
#375000
1%
#380000
b10101010 '
b10101010 1
b100010 &
b100010 0
b100010 .
0%
#385000
1%
#390000
b10011101 '
b10011101 1
b100011 &
b100011 0
b100011 .
0%
#395000
1%
#400000
b10010110 '
b10010110 1
b100100 &
b100100 0
b100100 .
0%
#405000
1%
#410000
b10011 '
b10011 1
b100101 &
b100101 0
b100101 .
0%
#415000
1%
#420000
b1101 '
b1101 1
b100110 &
b100110 0
b100110 .
0%
#425000
1%
#430000
b1010011 '
b1010011 1
b100111 &
b100111 0
b100111 .
0%
#435000
1%
#440000
b1101011 '
b1101011 1
b101000 &
b101000 0
b101000 .
0%
#445000
1%
#450000
b11010101 '
b11010101 1
b101001 &
b101001 0
b101001 .
0%
#455000
1%
#460000
b10 '
b10 1
b101010 &
b101010 0
b101010 .
0%
#465000
1%
#470000
b10101110 '
b10101110 1
b101011 &
b101011 0
b101011 .
0%
#475000
1%
#480000
b11101 '
b11101 1
b101100 &
b101100 0
b101100 .
0%
#485000
1%
#490000
b11001111 '
b11001111 1
b101101 &
b101101 0
b101101 .
0%
#495000
1%
#500000
b100011 '
b100011 1
b101110 &
b101110 0
b101110 .
0%
#505000
1%
#510000
b1010 '
b1010 1
b101111 &
b101111 0
b101111 .
0%
#515000
1%
#520000
b11001010 '
b11001010 1
b110000 &
b110000 0
b110000 .
0%
#525000
1%
#530000
b111100 '
b111100 1
b110001 &
b110001 0
b110001 .
0%
#535000
1%
#540000
b11110010 '
b11110010 1
b110010 &
b110010 0
b110010 .
0%
#545000
1%
#550000
b10001010 '
b10001010 1
b110011 &
b110011 0
b110011 .
0%
#555000
1%
#560000
b1000001 '
b1000001 1
b110100 &
b110100 0
b110100 .
0%
#565000
1%
#570000
b11011000 '
b11011000 1
b110101 &
b110101 0
b110101 .
0%
#575000
1%
#580000
b1111000 '
b1111000 1
b110110 &
b110110 0
b110110 .
0%
#585000
1%
#590000
b10001001 '
b10001001 1
b110111 &
b110111 0
b110111 .
0%
#595000
1%
#600000
b11101011 '
b11101011 1
b111000 &
b111000 0
b111000 .
0%
#605000
1%
#610000
b10110110 '
b10110110 1
b111001 &
b111001 0
b111001 .
0%
#615000
1%
#620000
b11000110 '
b11000110 1
b111010 &
b111010 0
b111010 .
0%
#625000
1%
#630000
b10101110 '
b10101110 1
b111011 &
b111011 0
b111011 .
0%
#635000
1%
#640000
b10111100 '
b10111100 1
b111100 &
b111100 0
b111100 .
0%
#645000
1%
#650000
b101010 '
b101010 1
b111101 &
b111101 0
b111101 .
0%
#655000
1%
#660000
b1011 '
b1011 1
b111110 &
b111110 0
b111110 .
0%
#665000
1%
#670000
b1110001 '
b1110001 1
b111111 &
b111111 0
b111111 .
0%
#675000
1%
#680000
b10000101 '
b10000101 1
b1000000 &
b1000000 0
b1000000 .
0%
#685000
1%
#690000
b1001111 '
b1001111 1
b1000001 &
b1000001 0
b1000001 .
0%
#695000
1%
#700000
b111011 '
b111011 1
b1000010 &
b1000010 0
b1000010 .
0%
#705000
1%
#710000
b111010 '
b111010 1
b1000011 &
b1000011 0
b1000011 .
0%
#715000
1%
#720000
b1111110 '
b1111110 1
b1000100 &
b1000100 0
b1000100 .
0%
#725000
1%
#730000
b10101 '
b10101 1
b1000101 &
b1000101 0
b1000101 .
0%
#735000
1%
#740000
b11110001 '
b11110001 1
b1000110 &
b1000110 0
b1000110 .
0%
#745000
1%
#750000
b11011001 '
b11011001 1
b1000111 &
b1000111 0
b1000111 .
0%
#755000
1%
#760000
b1100010 '
b1100010 1
b1001000 &
b1001000 0
b1001000 .
0%
#765000
1%
#770000
b1001100 '
b1001100 1
b1001001 &
b1001001 0
b1001001 .
0%
#775000
1%
#780000
b10011111 '
b10011111 1
b1001010 &
b1001010 0
b1001010 .
0%
#785000
1%
#790000
b10001111 '
b10001111 1
b1001011 &
b1001011 0
b1001011 .
0%
#795000
1%
#800000
b11111000 '
b11111000 1
b1001100 &
b1001100 0
b1001100 .
0%
#805000
1%
#810000
b10110111 '
b10110111 1
b1001101 &
b1001101 0
b1001101 .
0%
#815000
1%
#820000
b10011111 '
b10011111 1
b1001110 &
b1001110 0
b1001110 .
0%
#825000
1%
#830000
b1011100 '
b1011100 1
b1001111 &
b1001111 0
b1001111 .
0%
#835000
1%
#840000
b1011011 '
b1011011 1
b1010000 &
b1010000 0
b1010000 .
0%
#845000
1%
#850000
b10001001 '
b10001001 1
b1010001 &
b1010001 0
b1010001 .
0%
#855000
1%
#860000
b1001001 '
b1001001 1
b1010010 &
b1010010 0
b1010010 .
0%
#865000
1%
#870000
b11010000 '
b11010000 1
b1010011 &
b1010011 0
b1010011 .
0%
#875000
1%
#880000
0(
b1010100 .
0%
#885000
1%
#890000
1+
0%
#895000
0!
b1 7
b0 5
1%
#900000
0+
0%
#905000
b10 7
b0 6
b11111111111111111111111111111101 4
1%
#910000
0%
#915000
b1 6
b101100101 4
1%
#920000
0%
#925000
b10 6
b110111001100 4
1%
#930000
0%
#935000
b11 6
b110100011000 4
1%
#940000
0%
#945000
b100 6
b100110011101 4
1%
#950000
0%
#955000
b101 6
b101000111001 4
1%
#960000
0%
#965000
b110 6
b110011101011 4
1%
#970000
0%
#975000
b111 6
b10100000111 4
1%
#980000
0%
#985000
b1000 6
b10011010001 4
1%
#990000
0%
#995000
b1001 6
1%
#1000000
0%
#1005000
b1010 6
b1111100111 4
1%
#1010000
0%
#1015000
b1011 6
b10011010011 4
1%
#1020000
0%
#1025000
b1100 6
b10110001010 4
1%
#1030000
0%
#1035000
b1101 6
b10001101101 4
1%
#1040000
0%
#1045000
b1110 6
b11001101 4
1%
#1050000
0%
#1055000
b1111 6
b11010100 4
1%
#1060000
0%
#1065000
b10000 6
b1000110000 4
1%
#1070000
0%
#1075000
b10001 6
b10010011 4
1%
#1080000
0%
#1085000
b10010 6
b10011110001 4
1%
#1090000
0%
#1095000
b10011 6
b11111001010 4
1%
#1100000
0%
#1105000
b10100 6
b1110011011 4
1%
#1110000
0%
#1115000
b10101 6
b1000001111 4
1%
#1120000
0%
#1125000
b10110 6
b110100011000 4
1%
#1130000
0%
#1135000
b10111 6
b111001110110 4
1%
#1140000
0%
#1145000
b11000 6
b110011100110 4
1%
#1150000
0%
#1155000
b11001 6
b110000001110 4
1%
#1160000
0%
#1165000
b11010 6
b101011100111 4
1%
#1170000
0%
#1175000
b11011 6
b11111111111111111111110100111111 4
1%
#1180000
0%
#1185000
b11100 6
b11111111111111111111100110010101 4
1%
#1190000
0%
#1195000
b11101 6
b11111111111111111111101001110110 4
1%
#1200000
0%
#1205000
b11110 6
b11111111111111111111100101000111 4
1%
#1210000
0%
#1215000
b11111 6
b11111111111111111111010010100011 4
1%
#1220000
0%
#1225000
b100000 6
b11111111111111111111010010000101 4
1%
#1230000
0%
#1235000
b100001 6
b11111111111111111111000000000101 4
1%
#1240000
0%
#1245000
b100010 6
b11111111111111111111000011000101 4
1%
#1250000
0%
#1255000
b100011 6
b11111111111111111110110001100111 4
1%
#1260000
0%
#1265000
b100100 6
b11111111111111111110100000100110 4
1%
#1270000
0%
#1275000
b100101 6
b11111111111111111110101101110110 4
1%
#1280000
0%
#1285000
b100110 6
b11111111111111111110101001111111 4
1%
#1290000
0%
#1295000
b100111 6
b11111111111111111110101011011010 4
1%
#1300000
0%
#1305000
b101000 6
b11111111111111111110011111101111 4
1%
#1310000
0%
#1315000
b101001 6
b11111111111111111110101101000111 4
1%
#1320000
0%
#1325000
b101010 6
b11111111111111111111000011010010 4
1%
#1330000
0%
#1335000
b101011 6
b11111111111111111111000010101110 4
1%
#1340000
0%
#1345000
b101100 6
b11111111111111111111011000100000 4
1%
#1350000
0%
#1355000
b101101 6
b11111111111111111111010100111000 4
1%
#1360000
0%
#1365000
b101110 6
1%
#1370000
0%
#1375000
b101111 6
b11111111111111111111001111011010 4
1%
#1380000
0%
#1385000
b110000 6
b11111111111111111111010000101010 4
1%
#1390000
0%
#1395000
b110001 6
b11111111111111111111100000101100 4
1%
#1400000
0%
#1405000
b110010 6
b11111111111111111111100101011000 4
1%
#1410000
0%
#1415000
b110011 6
b11111111111111111111100110011110 4
1%
#1420000
0%
#1425000
b110100 6
b1011010110 4
1%
#1430000
0%
#1435000
b110101 6
b11010100101 4
1%
#1440000
0%
#1445000
b110110 6
b11110111101 4
1%
#1450000
0%
#1455000
b110111 6
b11111111111111111111110001111101 4
1%
#1460000
0%
#1465000
b111000 6
b11111111111111111111101110001111 4
1%
#1470000
0%
#1475000
b111001 6
b11111111111111111111110000100010 4
1%
#1480000
0%
#1485000
b111010 6
b11111111111111111111110100000000 4
1%
#1490000
0%
#1495000
b111011 6
b11111111111111111111111101111110 4
1%
#1500000
0%
#1505000
b111100 6
b11111111111111111111101001011110 4
1%
#1510000
0%
#1515000
b111101 6
b11111111111111111111100101001110 4
1%
#1520000
0%
#1525000
b111110 6
b11111111111111111111100111110110 4
1%
#1530000
0%
#1535000
b111111 6
b11111111111111111111101001111010 4
1%
#1540000
0%
#1545000
b1000000 6
b11111111111111111111011101100011 4
1%
#1550000
0%
#1555000
b1000001 6
b11111111111111111111000010101001 4
1%
#1560000
0%
#1565000
b1000010 6
b11111111111111111110111010000000 4
1%
#1570000
0%
#1575000
b1000011 6
b11111111111111111110010001011100 4
1%
#1580000
0%
#1585000
b1000100 6
b11111111111111111110010000100010 4
1%
#1590000
0%
#1595000
b1000101 6
b11111111111111111110101110000100 4
1%
#1600000
0%
#1605000
b1000110 6
b11111111111111111110110001000001 4
1%
#1610000
0%
#1615000
b1000111 6
b11111111111111111110110101111100 4
1%
#1620000
0%
#1625000
b1001000 6
b11111111111111111110110010010010 4
1%
#1630000
0%
#1635000
b1001001 6
b11111111111111111110101010101000 4
1%
#1640000
0%
#1645000
b1001010 6
b11111111111111111110100001001000 4
1%
#1650000
0%
#1655000
b1001011 6
b11111111111111111101111011001111 4
1%
#1660000
0%
#1665000
b1001100 6
b11111111111111111110010000011011 4
1%
#1670000
0%
#1675000
b1001101 6
b11111111111111111110001111111011 4
1%
#1680000
0%
#1685000
b1001110 6
b11111111111111111101111111111101 4
1%
#1690000
0%
#1695000
b1001111 6
b11111111111111111101111000011000 4
1%
#1700000
0%
#1705000
b1010000 6
b11111111111111111110000011111000 4
1%
#1710000
0%
#1715000
b1010001 6
b11111111111111111101111110001100 4
1%
#1720000
0%
#1725000
b1010010 6
b11111111111111111110010100100000 4
1%
#1730000
0%
#1735000
b1010011 6
b11111111111111111110010111111011 4
1%
#1740000
0%
#1745000
b11 7
b11111111111111111110011001011011 4
1%
#1750000
0%
#1755000
b1 7
b1 5
b11111111111111111110011001011011 "
b11111111111111111110011001011011 3
1%
#1760000
0%
#1765000
b10 7
b0 6
b100 4
1%
#1770000
0%
#1775000
b1 6
b11111111111111111111111110111100 4
1%
#1780000
0%
#1785000
b10 6
b110111000 4
1%
#1790000
0%
#1795000
b11 6
b110101111 4
1%
#1800000
0%
#1805000
b100 6
b10111110000 4
1%
#1810000
0%
#1815000
b101 6
b10111111101 4
1%
#1820000
0%
#1825000
b110 6
b100110010101 4
1%
#1830000
0%
#1835000
b111 6
b11101 4
1%
#1840000
0%
#1845000
b1000 6
b100011001 4
1%
#1850000
0%
#1855000
b1001 6
b100101011 4
1%
#1860000
0%
#1865000
b1010 6
b111100001 4
1%
#1870000
0%
#1875000
b1011 6
b11111111111111111111101111100011 4
1%
#1880000
0%
#1885000
b1100 6
b11111111111111111111011101011100 4
1%
#1890000
0%
#1895000
b1101 6
b11111111111111111111100011111110 4
1%
#1900000
0%
#1905000
b1110 6
b11111111111111111111100111100110 4
1%
#1910000
0%
#1915000
b1111 6
1%
#1920000
0%
#1925000
b10000 6
b11111111111111111111111000110100 4
1%
#1930000
0%
#1935000
b10001 6
b11111111111111111111110000100001 4
1%
#1940000
0%
#1945000
b10010 6
b11111111111111111111011111000011 4
1%
#1950000
0%
#1955000
b10011 6
b11111111111111111111101011101101 4
1%
#1960000
0%
#1965000
b10100 6
b11111111111111111110110101110010 4
1%
#1970000
0%
#1975000
b10101 6
b11111111111111111110111000100110 4
1%
#1980000
0%
#1985000
b10110 6
b11111111111111111110111101111001 4
1%
#1990000
0%
#1995000
b10111 6
b11111111111111111111000011001001 4
1%
#2000000
0%
#2005000
b11000 6
b11111111111111111111000111000011 4
1%
#2010000
0%
#2015000
b11001 6
b11111111111111111111001000100011 4
1%
#2020000
0%
#2025000
b11010 6
b11111111111111111110111110011010 4
1%
#2030000
0%
#2035000
b11011 6
b11111111111111111111000101100110 4
1%
#2040000
0%
#2045000
b11100 6
b11111111111111111111010001000111 4
1%
#2050000
0%
#2055000
b11101 6
b11111111111111111111001111101101 4
1%
#2060000
0%
#2065000
b11110 6
b11111111111111111110111110010110 4
1%
#2070000
0%
#2075000
b11111 6
b11111111111111111110111111111001 4
1%
#2080000
0%
#2085000
b100000 6
b11111111111111111110111110111101 4
1%
#2090000
0%
#2095000
b100001 6
b11111111111111111110010100111101 4
1%
#2100000
0%
#2105000
b100010 6
b11111111111111111110001111111101 4
1%
#2110000
0%
#2115000
b100011 6
b11111111111111111101110110011011 4
1%
#2120000
0%
#2125000
b100100 6
b11111111111111111101111110001010 4
1%
#2130000
0%
#2135000
b100101 6
b11111111111111111110100100010000 4
1%
#2140000
0%
#2145000
b100110 6
b11111111111111111110011100110101 4
1%
#2150000
0%
#2155000
b100111 6
b11111111111111111110011001011000 4
1%
#2160000
0%
#2165000
b101000 6
b11111111111111111110110101111010 4
1%
#2170000
0%
#2175000
b101001 6
b11111111111111111110111001010000 4
1%
#2180000
0%
#2185000
b101010 6
b11111111111111111110110010100010 4
1%
#2190000
0%
#2195000
b101011 6
b11111111111111111110110001111000 4
1%
#2200000
0%
#2205000
b101100 6
b11111111111111111110100011110010 4
1%
#2210000
0%
#2215000
b101101 6
b11111111111111111110101000110001 4
1%
#2220000
0%
#2225000
b101110 6
b11111111111111111110110001111101 4
1%
#2230000
0%
#2235000
b101111 6
b11111111111111111110101110001000 4
1%
#2240000
0%
#2245000
b110000 6
b11111111111111111110101110011100 4
1%
#2250000
0%
#2255000
b110001 6
b11111111111111111110100110110110 4
1%
#2260000
0%
#2265000
b110010 6
b11111111111111111110110001001010 4
1%
#2270000
0%
#2275000
b110011 6
b11111111111111111110110011010110 4
1%
#2280000
0%
#2285000
b110100 6
b11111111111111111111010000110110 4
1%
#2290000
0%
#2295000
b110101 6
b11111111111111111111001101110011 4
1%
#2300000
0%
#2305000
b110110 6
b11111111111111111111000110010011 4
1%
#2310000
0%
#2315000
b110111 6
b11111111111111111110000110100011 4
1%
#2320000
0%
#2325000
b111000 6
b11111111111111111110001101111111 4
1%
#2330000
0%
#2335000
b111001 6
b11111111111111111110010010111010 4
1%
#2340000
0%
#2345000
b111010 6
b11111111111111111110010100000100 4
1%
#2350000
0%
#2355000
b111011 6
b11111111111111111110010001010110 4
1%
#2360000
0%
#2365000
b111100 6
b11111111111111111110000101110100 4
1%
#2370000
0%
#2375000
b111101 6
b11111111111111111101111011001100 4
1%
#2380000
0%
#2385000
b111110 6
b11111111111111111101111111001000 4
1%
#2390000
0%
#2395000
b111111 6
b11111111111111111101111111010011 4
1%
#2400000
0%
#2405000
b1000000 6
b11111111111111111101110001001011 4
1%
#2410000
0%
#2415000
b1000001 6
b11111111111111111110000000100011 4
1%
#2420000
0%
#2425000
b1000010 6
b11111111111111111101110010111110 4
1%
#2430000
0%
#2435000
b1000011 6
b11111111111111111101110010000011 4
1%
#2440000
0%
#2445000
b1000100 6
b11111111111111111101010011001111 4
1%
#2450000
0%
#2455000
b1000101 6
b11111111111111111100000000100011 4
1%
#2460000
0%
#2465000
b1000110 6
b11111111111111111011111111100100 4
1%
#2470000
0%
#2475000
b1000111 6
b11111111111111111100000101001100 4
1%
#2480000
0%
#2485000
b1001000 6
b11111111111111111100000001100010 4
1%
#2490000
0%
#2495000
b1001001 6
b11111111111111111011101111001010 4
1%
#2500000
0%
#2505000
b1001010 6
b11111111111111111011111101011010 4
1%
#2510000
0%
#2515000
b1001011 6
b11111111111111111100000000011100 4
1%
#2520000
0%
#2525000
b1001100 6
b11111111111111111011100010011011 4
1%
#2530000
0%
#2535000
b1001101 6
b11111111111111111011100000011011 4
1%
#2540000
0%
#2545000
b1001110 6
b11111111111111111011100100111111 4
1%
#2550000
0%
#2555000
b1001111 6
b11111111111111111011101111100110 4
1%
#2560000
0%
#2565000
b1010000 6
b11111111111111111011101100101110 4
1%
#2570000
0%
#2575000
b1010001 6
b11111111111111111011100010110001 4
1%
#2580000
0%
#2585000
b1010010 6
b11111111111111111011010000001011 4
1%
#2590000
0%
#2595000
b1010011 6
b11111111111111111011011001010011 4
1%
#2600000
0%
#2605000
b11 7
b11111111111111111011100011110011 4
1%
#2610000
0%
#2615000
b1 7
b10 5
1%
#2620000
0%
#2625000
b10 7
b0 6
b11111111111111111111111111010011 4
1%
#2630000
0%
#2635000
b1 6
b100010111 4
1%
#2640000
0%
#2645000
b10 6
b11111111111111111111110000100001 4
1%
#2650000
0%
#2655000
b11 6
b11111111111111111111110000000110 4
1%
#2660000
0%
#2665000
b100 6
b111010011 4
1%
#2670000
0%
#2675000
b101 6
b10011011 4
1%
#2680000
0%
#2685000
b110 6
b11111111111111111111110100000011 4
1%
#2690000
0%
#2695000
b111 6
b11111111111111111111000001100011 4
1%
#2700000
0%
#2705000
b1000 6
b11111111111111111111000111011101 4
1%
#2710000
0%
#2715000
b1001 6
b11111111111111111111000111101011 4
1%
#2720000
0%
#2725000
b1010 6
b11111111111111111111001000011111 4
1%
#2730000
0%
#2735000
b1011 6
b11111111111111111110111101011011 4
1%
#2740000
0%
#2745000
b1100 6
b11111111111111111110100011101100 4
1%
#2750000
0%
#2755000
b1101 6
b11111111111111111110101010100001 4
1%
#2760000
0%
#2765000
b1110 6
b11111111111111111110001111010101 4
1%
#2770000
0%
#2775000
b1111 6
b11111111111111111110001111001110 4
1%
#2780000
0%
#2785000
b10000 6
b11111111111111111101111010011000 4
1%
#2790000
0%
#2795000
b10001 6
b11111111111111111101111100001110 4
1%
#2800000
0%
#2805000
b10010 6
b11111111111111111110001011000000 4
1%
#2810000
0%
#2815000
b10011 6
b11111111111111111110001011011011 4
1%
#2820000
0%
#2825000
b10100 6
b11111111111111111110011111111000 4
1%
#2830000
0%
#2835000
b10101 6
b11111111111111111110011010110100 4
1%
#2840000
0%
#2845000
b10110 6
b11111111111111111110100111001011 4
1%
#2850000
0%
#2855000
b10111 6
b11111111111111111110100100110001 4
1%
#2860000
0%
#2865000
b11000 6
b11111111111111111110101011000001 4
1%
#2870000
0%
#2875000
b11001 6
b11111111111111111110100100010001 4
1%
#2880000
0%
#2885000
b11010 6
b11111111111111111110111101001010 4
1%
#2890000
0%
#2895000
b11011 6
b11111111111111111111001100111110 4
1%
#2900000
0%
#2905000
b11100 6
b11111111111111111111000010100000 4
1%
#2910000
0%
#2915000
b11101 6
b11111111111111111111001010111100 4
1%
#2920000
0%
#2925000
b11110 6
b11111111111111111110010011101101 4
1%
#2930000
0%
#2935000
b11111 6
b11111111111111111110011011011100 4
1%
#2940000
0%
#2945000
b100000 6
b11111111111111111110011010101010 4
1%
#2950000
0%
#2955000
b100001 6
b11111111111111111111001100101010 4
1%
#2960000
0%
#2965000
b100010 6
b11111111111111111111010011101010 4
1%
#2970000
0%
#2975000
b100011 6
b11111111111111111110111110001010 4
1%
#2980000
0%
#2985000
b100100 6
b11111111111111111111010110111010 4
1%
#2990000
0%
#2995000
b100101 6
b11111111111111111111101100011100 4
1%
#3000000
0%
#3005000
b100110 6
b11111111111111111111101101111011 4
1%
#3010000
0%
#3015000
b100111 6
b11111111111111111111101100100000 4
1%
#3020000
0%
#3025000
b101000 6
b11111111111111111111101101110011 4
1%
#3030000
0%
#3035000
b101001 6
b1110111 4
1%
#3040000
0%
#3045000
b101010 6
b11111111111111111111111011110100 4
1%
#3050000
0%
#3055000
b101011 6
b11111111111111111111111011100010 4
1%
#3060000
0%
#3065000
b101100 6
b10011111000 4
1%
#3070000
0%
#3075000
b101101 6
b11000110111 4
1%
#3080000
0%
#3085000
b101110 6
b100101000111 4
1%
#3090000
0%
#3095000
b101111 6
b110000100110 4
1%
#3100000
0%
#3105000
b110000 6
b101101101000 4
1%
#3110000
0%
#3115000
b110001 6
b100110000010 4
1%
#3120000
0%
#3125000
b110010 6
b10110000110 4
1%
#3130000
0%
#3135000
b110011 6
b11001001010 4
1%
#3140000
0%
