rtl/pool2.v
`timescale 1ns / 1ps
// =============================================================
// POOL2 : Max-pooling 2x2, stride 2
// Vao : 16 x 11 x 11  (1936 gia tri, dia chi 11 bit)
// Ra  : 16 x 5  x 5   (400 gia tri, dia chi 9 bit)
// =============================================================
module pool2 (
    input  wire        clk,
    input  wire        rst_n,

    input  wire        start,
    output wire        ready,
    output reg         done,

    input  wire        in_wr_en,
    input  wire [10:0] in_wr_addr,
    input  wire signed [7:0] in_wr_data,

    input  wire [8:0]  out_rd_addr,
    output wire signed [7:0]  out_rd_data
);

    reg signed [7:0] c2_out [0:1935];
    reg signed [7:0] p2_out [0:399];

    always @(posedge clk) begin
        if (in_wr_en) c2_out[in_wr_addr] <= in_wr_data;
    end
    assign out_rd_data = p2_out[out_rd_addr];

    localparam IDLE = 0, INIT = 1, COMP = 2, STORE = 3;
    reg [2:0] state;

    reg [15:0] c, y, x, ky, kx;
    reg signed [31:0] max_val;

    assign ready = (state == IDLE);

    always @(posedge clk or negedge rst_n) begin
        if (!rst_n) begin
            state <= IDLE;
            done  <= 0;
        end else begin
            done <= 0;
            case (state)
                IDLE: begin
                    if (start) begin
                        c <= 0; y <= 0; x <= 0;
                        state <= INIT;
                    end
                end

                INIT: begin
                    max_val <= -128;
                    ky <= 0; kx <= 0;
                    state <= COMP;
                end

                COMP: begin
                    if (c2_out[c*121 + (y*2+ky)*11 + (x*2+kx)] > max_val)
                        max_val <= c2_out[c*121 + (y*2+ky)*11 + (x*2+kx)];

                    if (kx == 1) begin
                        kx <= 0;
                        if (ky == 1) state <= STORE;
                        else ky <= ky + 1;
                    end else kx <= kx + 1;
                end

                STORE: begin
                    p2_out[c*25 + y*5 + x] <= max_val[7:0];
                    if (x == 4) begin
                        x <= 0;
                        if (y == 4) begin
                            y <= 0;
                            if (c == 15) begin
                                done  <= 1;
                                state <= IDLE;
                            end else begin
                                c <= c + 1;
                                state <= INIT;
                            end
                        end else begin y <= y + 1; state <= INIT; end
                    end else begin x <= x + 1; state <= INIT; end
                end
            endcase
        end
    end
endmodule

testbench/tb_pool2.v
`timescale 1ns / 1ps
// =============================================================
// TB_POOL2 : Kiem tra doc lap module pool2 (max-pool 2x2)
// =============================================================
module tb_pool2;

    reg clk, rst_n, start;
    wire ready, done;

    reg         in_wr_en;
    reg [10:0]  in_wr_addr;
    reg signed [7:0] in_wr_data;

    reg  [8:0]  out_rd_addr;
    wire signed [7:0] out_rd_data;

    pool2 dut (
        .clk(clk), .rst_n(rst_n),
        .start(start), .ready(ready), .done(done),
        .in_wr_en(in_wr_en), .in_wr_addr(in_wr_addr), .in_wr_data(in_wr_data),
        .out_rd_addr(out_rd_addr), .out_rd_data(out_rd_data)
    );

    initial clk = 0;
    always #5 clk = ~clk;

    // Xuat waveform ra file .vcd de xem bang GTKWave
    initial begin
        $dumpfile("pool2.vcd");
        $dumpvars(0, tb_pool2);
    end

    reg signed [7:0] ref_in  [0:1935];
    reg signed [7:0] ref_out [0:399];

    integer c, y, x, ky, kx, i, errors;
    reg signed [31:0] max_val;

    task compute_reference;
        begin
            for (c = 0; c < 16; c = c + 1) begin
                for (y = 0; y < 5; y = y + 1) begin
                    for (x = 0; x < 5; x = x + 1) begin
                        max_val = -128;
                        for (ky = 0; ky < 2; ky = ky + 1)
                            for (kx = 0; kx < 2; kx = kx + 1)
                                if (ref_in[c*121 + (y*2+ky)*11 + (x*2+kx)] > max_val)
                                    max_val = ref_in[c*121 + (y*2+ky)*11 + (x*2+kx)];
                        ref_out[c*25 + y*5 + x] = max_val[7:0];
                    end
                end
            end
        end
    endtask

    initial begin
        rst_n = 0; start = 0; in_wr_en = 0; in_wr_addr = 0; in_wr_data = 0;
        out_rd_addr = 0; errors = 0;

        repeat (3) @(posedge clk);
        @(negedge clk); rst_n = 1;

        for (i = 0; i < 1936; i = i + 1)
            ref_in[i] = $random;

        compute_reference;

        @(negedge clk);
        for (i = 0; i < 1936; i = i + 1) begin
            in_wr_en   = 1;
            in_wr_addr = i[10:0];
            in_wr_data = ref_in[i];
            @(negedge clk);
        end
        in_wr_en = 0;

        wait (ready);
        @(negedge clk); start = 1;
        @(negedge clk); start = 0;

        wait (done);
        @(negedge clk);

        for (i = 0; i < 400; i = i + 1) begin
            out_rd_addr = i[8:0];
            #1;
            if (out_rd_data !== ref_out[i]) begin
                errors = errors + 1;
                if (errors <= 10)
                    $display("[SAI] idx=%0d rtl=%0d ref=%0d", i, out_rd_data, ref_out[i]);
            end
        end

        if (errors == 0)
            $display("\n[PASS] pool2: tat ca 400 gia tri dau ra khop voi mo hinh tham chieu.\n");
        else
            $display("\n[FAIL] pool2: %0d / 400 gia tri sai khac.\n", errors);

        #20 $finish;
    end

    initial begin
        #500000;
        $display("[WATCHDOG] tb_pool2 qua thoi gian cho!");
        $finish;
    end
endmodule

results/pool2.vcd
$date
	Thu Jul 23 23:54:45 2026
$end
$version
	Icarus Verilog
$end
$timescale
	1ps
$end
$scope module tb_pool2 $end
$var wire 1 ! ready $end
$var wire 8 " out_rd_data [7:0] $end
$var wire 1 # done $end
$var reg 1 $ clk $end
$var reg 11 % in_wr_addr [10:0] $end
$var reg 8 & in_wr_data [7:0] $end
$var reg 1 ' in_wr_en $end
$var reg 32 ( max_val [31:0] $end
$var reg 9 ) out_rd_addr [8:0] $end
$var reg 1 * rst_n $end
$var reg 1 + start $end
$var integer 32 , c [31:0] $end
$var integer 32 - errors [31:0] $end
$var integer 32 . i [31:0] $end
$var integer 32 / kx [31:0] $end
$var integer 32 0 ky [31:0] $end
$var integer 32 1 x [31:0] $end
$var integer 32 2 y [31:0] $end
$scope module dut $end
$var wire 1 $ clk $end
$var wire 11 3 in_wr_addr [10:0] $end
$var wire 8 4 in_wr_data [7:0] $end
$var wire 1 ' in_wr_en $end
$var wire 9 5 out_rd_addr [8:0] $end
$var wire 8 6 out_rd_data [7:0] $end
$var wire 1 * rst_n $end
$var wire 1 + start $end
$var wire 1 ! ready $end
$var reg 16 7 c [15:0] $end
$var reg 1 # done $end
$var reg 16 8 kx [15:0] $end
$var reg 16 9 ky [15:0] $end
$var reg 32 : max_val [31:0] $end
$var reg 3 ; state [2:0] $end
$var reg 16 < x [15:0] $end
$var reg 16 = y [15:0] $end
$upscope $end
$scope task compute_reference $end
$upscope $end
$upscope $end
$enddefinitions $end
#0
$dumpvars
bx =
bx <
b0 ;
bx :
bx 9
bx 8
bx 7
bx 6
b0 5
b0 4
b0 3
bx 2
bx 1
bx 0
bx /
bx .
b0 -
bx ,
0+
0*
b0 )
bx (
0'
b0 &
b0 %
0$
0#
bx "
1!
$end
#5000
1$
#10000
0$
#15000
1$
#20000
0$
#25000
1$
#30000
b10 /
b10 0
b1110110 (
b101 1
b101 2
b10000 ,
b11110010000 .
1*
0$
#35000
1$
#40000
b100100 &
b100100 4
1'
b0 .
0$
#45000
1$
#50000
b10000001 &
b10000001 4
b1 %
b1 3
b1 .
0$
#55000
1$
#60000
b1001 &
b1001 4
b10 %
b10 3
b10 .
0$
#65000
1$
#70000
b1100011 &
b1100011 4
b11 %
b11 3
b11 .
0$
#75000
1$
#80000
b1101 &
b1101 4
b100 %
b100 3
b100 .
0$
#85000
1$
#90000
b10001101 &
b10001101 4
b101 %
b101 3
b101 .
0$
#95000
1$
#100000
b1100101 &
b1100101 4
b110 %
b110 3
b110 .
0$
#105000
1$
#110000
b10010 &
b10010 4
b111 %
b111 3
b111 .
0$
#115000
1$
#120000
b1 &
b1 4
b1000 %
b1000 3
b1000 .
0$
#125000
1$
#130000
b1101 &
b1101 4
b1001 %
b1001 3
b1001 .
0$
#135000
1$
#140000
b1110110 &
b1110110 4
b1010 %
b1010 3
b1010 .
0$
#145000
1$
#150000
b111101 &
b111101 4
b1011 %
b1011 3
b1011 .
0$
#155000
1$
#160000
b11101101 &
b11101101 4
b1100 %
b1100 3
b1100 .
0$
#165000
1$
#170000
b10001100 &
b10001100 4
b1101 %
b1101 3
b1101 .
0$
#175000
1$
#180000
b11111001 &
b11111001 4
b1110 %
b1110 3
b1110 .
0$
#185000
1$
#190000
b11000110 &
b11000110 4
b1111 %
b1111 3
b1111 .
0$
#195000
1$
#200000
b11000101 &
b11000101 4
b10000 %
b10000 3
b10000 .
0$
#205000
1$
#210000
b10101010 &
b10101010 4
b10001 %
b10001 3
b10001 .
0$
#215000
1$
#220000
b11100101 &
b11100101 4
b10010 %
b10010 3
b10010 .
0$
#225000
1$
#230000
b1110111 &
b1110111 4
b10011 %
b10011 3
b10011 .
0$
#235000
1$
#240000
b10010 &
b10010 4
b10100 %
b10100 3
b10100 .
0$
#245000
1$
#250000
b10001111 &
b10001111 4
b10101 %
b10101 3
b10101 .
0$
#255000
1$
#260000
b11110010 &
b11110010 4
b10110 %
b10110 3
b10110 .
0$
#265000
1$
#270000
b11001110 &
b11001110 4
b10111 %
b10111 3
b10111 .
0$
#275000
1$
#280000
b11101000 &
b11101000 4
b11000 %
b11000 3
b11000 .
0$
#285000
1$
#290000
b11000101 &
b11000101 4
b11001 %
b11001 3
b11001 .
0$
#295000
1$
#300000
b1011100 &
b1011100 4
b11010 %
b11010 3
b11010 .
0$
#305000
1$
#310000
b10111101 &
b10111101 4
b11011 %
b11011 3
b11011 .
0$
#315000
1$
#320000
b101101 &
b101101 4
b11100 %
b11100 3
b11100 .
0$
#325000
1$
#330000
b1100101 &
b1100101 4
b11101 %
b11101 3
b11101 .
0$
#335000
1$
#340000
b1100011 &
b1100011 4
b11110 %
b11110 3
b11110 .
0$
#345000
1$
#350000
b1010 &
b1010 4
b11111 %
b11111 3
b11111 .
0$
#355000
1$
#360000
b10000000 &
b10000000 4
b100000 %
b100000 3
b100000 .
0$
#365000
1$
#370000
b100000 &
b100000 4
b100001 %
b100001 3
b100001 .
0$
#375000
1$
#380000
b10101010 &
b10101010 4
b100010 %
b100010 3
b100010 .
0$
#385000
1$
#390000
b10011101 &
b10011101 4
b100011 %
b100011 3
b100011 .
0$
#395000
1$
#400000
b10010110 &
b10010110 4
b100100 %
b100100 3
b100100 .
0$
#405000
1$
#410000
b10011 &
b10011 4
b100101 %
b100101 3
b100101 .
0$
#415000
1$
#420000
b1101 &
b1101 4
b100110 %
b100110 3
b100110 .
0$
#425000
1$
#430000
b1010011 &
b1010011 4
b100111 %
b100111 3
b100111 .
0$
#435000
1$
#440000
b1101011 &
b1101011 4
b101000 %
b101000 3
b101000 .
0$
#445000
1$
#450000
b11010101 &
b11010101 4
b101001 %
b101001 3
b101001 .
0$
#455000
1$
#460000
b10 &
b10 4
b101010 %
b101010 3
b101010 .
0$
#465000
1$
#470000
b10101110 &
b10101110 4
b101011 %
b101011 3
b101011 .
0$
#475000
1$
#480000
b11101 &
b11101 4
b101100 %
b101100 3
b101100 .
0$
#485000
1$
#490000
b11001111 &
b11001111 4
b101101 %
b101101 3
b101101 .
0$
#495000
1$
#500000
b100011 &
b100011 4
b101110 %
b101110 3
b101110 .
0$
#505000
1$
#510000
b1010 &
b1010 4
b101111 %
b101111 3
b101111 .
0$
#515000
1$
#520000
b11001010 &
b11001010 4
b110000 %
b110000 3
b110000 .
0$
#525000
1$
#530000
b111100 &
b111100 4
b110001 %
b110001 3
b110001 .
0$
#535000
1$
#540000
b11110010 &
b11110010 4
b110010 %
b110010 3
b110010 .
0$
#545000
1$
#550000
b10001010 &
b10001010 4
b110011 %
b110011 3
b110011 .
0$
#555000
1$
#560000
b1000001 &
b1000001 4
b110100 %
b110100 3
b110100 .
0$
#565000
1$
#570000
b11011000 &
b11011000 4
b110101 %
b110101 3
b110101 .
0$
#575000
1$
#580000
b1111000 &
b1111000 4
b110110 %
b110110 3
b110110 .
0$
#585000
1$
#590000
b10001001 &
b10001001 4
b110111 %
b110111 3
b110111 .
0$
#595000
1$
#600000
b11101011 &
b11101011 4
b111000 %
b111000 3
b111000 .
0$
#605000
1$
#610000
b10110110 &
b10110110 4
b111001 %
b111001 3
b111001 .
0$
#615000
1$
#620000
b11000110 &
b11000110 4
b111010 %
b111010 3
b111010 .
0$
#625000
1$
#630000
b10101110 &
b10101110 4
b111011 %
b111011 3
b111011 .
0$
#635000
1$
#640000
b10111100 &
b10111100 4
b111100 %
b111100 3
b111100 .
0$
#645000
1$
#650000
b101010 &
b101010 4
b111101 %
b111101 3
b111101 .
0$
#655000
1$
#660000
b1011 &
b1011 4
b111110 %
b111110 3
b111110 .
0$
#665000
1$
#670000
b1110001 &
b1110001 4
b111111 %
b111111 3
b111111 .
0$
#675000
1$
#680000
b10000101 &
b10000101 4
b1000000 %
b1000000 3
b1000000 .
0$
#685000
1$
#690000
b1001111 &
b1001111 4
b1000001 %
b1000001 3
b1000001 .
0$
#695000
1$
#700000
b111011 &
b111011 4
b1000010 %
b1000010 3
b1000010 .
0$
#705000
1$
#710000
b111010 &
b111010 4
b1000011 %
b1000011 3
b1000011 .
0$
#715000
1$
#720000
b1111110 &
b1111110 4
b1000100 %
b1000100 3
b1000100 .
0$
#725000
1$
#730000
b10101 &
b10101 4
b1000101 %
b1000101 3
b1000101 .
0$
#735000
1$
#740000
b11110001 &
b11110001 4
b1000110 %
b1000110 3
b1000110 .
0$
#745000
1$
#750000
b11011001 &
b11011001 4
b1000111 %
b1000111 3
b1000111 .
0$
#755000
1$
#760000
b1100010 &
b1100010 4
b1001000 %
b1001000 3
b1001000 .
0$
#765000
1$
#770000
b1001100 &
b1001100 4
b1001001 %
b1001001 3
b1001001 .
0$
#775000
1$
#780000
b10011111 &
b10011111 4
b1001010 %
b1001010 3
b1001010 .
0$
#785000
1$
#790000
b10001111 &
b10001111 4
b1001011 %
b1001011 3
b1001011 .
0$
#795000
1$
#800000
b11111000 &
b11111000 4
b1001100 %
b1001100 3
b1001100 .
0$
#805000
1$
#810000
b10110111 &
b10110111 4
b1001101 %
b1001101 3
b1001101 .
0$
#815000
1$
#820000
b10011111 &
b10011111 4
b1001110 %
b1001110 3
b1001110 .
0$
#825000
1$
#830000
b1011100 &
b1011100 4
b1001111 %
b1001111 3
b1001111 .
0$
#835000
1$
#840000
b1011011 &
b1011011 4
b1010000 %
b1010000 3
b1010000 .
0$
#845000
1$
#850000
b10001001 &
b10001001 4
b1010001 %
b1010001 3
b1010001 .
0$
#855000
1$
#860000
b1001001 &
b1001001 4
b1010010 %
b1010010 3
b1010010 .
0$
#865000
1$
#870000
b11010000 &
b11010000 4
b1010011 %
b1010011 3
b1010011 .
0$
#875000
1$
#880000
b11010111 &
b11010111 4
b1010100 %
b1010100 3
b1010100 .
0$
#885000
1$
#890000
b1010001 &
b1010001 4
b1010101 %
b1010101 3
b1010101 .
0$
#895000
1$
#900000
b10010110 &
b10010110 4
b1010110 %
b1010110 3
b1010110 .
0$
#905000
1$
#910000
b1100 &
b1100 4
b1010111 %
b1010111 3
b1010111 .
0$
#915000
1$
#920000
b11000010 &
b11000010 4
b1011000 %
b1011000 3
b1011000 .
0$
#925000
1$
#930000
b11001000 &
b11001000 4
b1011001 %
b1011001 3
b1011001 .
0$
#935000
1$
#940000
b1110111 &
b1110111 4
b1011010 %
b1011010 3
b1011010 .
0$
#945000
1$
#950000
b111101 &
b111101 4
b1011011 %
b1011011 3
b1011011 .
0$
#955000
1$
#960000
b10010 &
b10010 4
b1011100 %
b1011100 3
b1011100 .
0$
#965000
1$
#970000
b1111110 &
b1111110 4
b1011101 %
b1011101 3
b1011101 .
0$
#975000
1$
#980000
b1101101 &
b1101101 4
b1011110 %
b1011110 3
b1011110 .
0$
#985000
1$
#990000
b111001 &
b111001 4
b1011111 %
b1011111 3
b1011111 .
0$
#995000
1$
#1000000
b11111 &
b11111 4
b1100000 %
b1100000 3
b1100000 .
0$
#1005000
1$
#1010000
b11010011 &
b11010011 4
b1100001 %
b1100001 3
b1100001 .
0$
#1015000
1$
#1020000
b10000101 &
b10000101 4
b1100010 %
b1100010 3
b1100010 .
0$
#1025000
1$
#1030000
b1111000 &
b1111000 4
b1100011 %
b1100011 3
b1100011 .
0$
#1035000
1$
#1040000
b1011011 &
b1011011 4
b1100100 %
b1100100 3
b1100100 .
0$
#1045000
1$
#1050000
b1001001 &
b1001001 4
b1100101 %
b1100101 3
b1100101 .
0$
#1055000
1$
#1060000
b111111 &
b111111 4
b1100110 %
b1100110 3
b1100110 .
0$
#1065000
1$
#1070000
b101010 &
b101010 4
b1100111 %
b1100111 3
b1100111 .
0$
#1075000
1$
#1080000
b1011000 &
b1011000 4
b1101000 %
b1101000 3
b1101000 .
0$
#1085000
1$
#1090000
b10000110 &
b10000110 4
b1101001 %
b1101001 3
b1101001 .
0$
#1095000
1$
#1100000
b10001110 &
b10001110 4
b1101010 %
b1101010 3
b1101010 .
0$
#1105000
1$
#1110000
b10011100 &
b10011100 4
b1101011 %
b1101011 3
b1101011 .
0$
#1115000
1$
#1120000
b11111010 &
b11111010 4
b1101100 %
b1101100 3
b1101100 .
0$
#1125000
1$
#1130000
b100110 &
b100110 4
b1101101 %
b1101101 3
b1101101 .
0$
#1135000
1$
#1140000
b1110011 &
b1110011 4
b1101110 %
b1101110 3
b1101110 .
0$
#1145000
1$
#1150000
b10100011 &
b10100011 4
b1101111 %
b1101111 3
b1101111 .
0$
#1155000
1$
#1160000
b101111 &
b101111 4
b1110000 %
b1110000 3
b1110000 .
0$
#1165000
1$
#1170000
b10110011 &
b10110011 4
b1110001 %
b1110001 3
b1110001 .
0$
#1175000
1$
#1180000
b1011111 &
b1011111 4
b1110010 %
b1110010 3
b1110010 .
0$
#1185000
1$
#1190000
b1000100 &
b1000100 4
b1110011 %
b1110011 3
b1110011 .
0$
#1195000
1$
#1200000
b11110111 &
b11110111 4
b1110100 %
b1110100 3
b1110100 .
0$
#1205000
1$
#1210000
b11001011 &
b11001011 4
b1110101 %
b1110101 3
b1110101 .
0$
#1215000
1$
#1220000
b11100110 &
b11100110 4
b1110110 %
b1110110 3
b1110110 .
0$
#1225000
1$
#1230000
b1011010 &
b1011010 4
b1110111 %
b1110111 3
b1110111 .
0$
#1235000
1$
#1240000
b101001 &
b101001 4
b1111000 %
b1111000 3
b1111000 .
0$
#1245000
1$
#1250000
b11101101 &
b11101101 4
b1111001 %
b1111001 3
b1111001 .
0$
#1255000
1$
#1260000
b11011010 &
b11011010 4
b1111010 %
b1111010 3
b1111010 .
0$
#1265000
1$
#1270000
b1100101 &
b1100101 4
b1111011 %
b1111011 3
b1111011 .
0$
#1275000
1$
#1280000
b10110101 &
b10110101 4
b1111100 %
b1111100 3
b1111100 .
0$
#1285000
1$
#1290000
b11011111 &
b11011111 4
b1111101 %
b1111101 3
b1111101 .
0$
#1295000
1$
#1300000
b1111001 &
b1111001 4
b1111110 %
b1111110 3
b1111110 .
0$
#1305000
1$
#1310000
b1000100 &
b1000100 4
b1111111 %
b1111111 3
b1111111 .
0$
#1315000
1$
#1320000
b11010000 &
b11010000 4
b10000000 %
b10000000 3
b10000000 .
0$
#1325000
1$
#1330000
b101010 &
b101010 4
b10000001 %
b10000001 3
b10000001 .
0$
#1335000
1$
#1340000
b10101011 &
b10101011 4
b10000010 %
b10000010 3
b10000010 .
0$
#1345000
1$
#1350000
b1110 &
b1110 4
b10000011 %
b10000011 3
b10000011 .
0$
#1355000
1$
#1360000
b11011100 &
b11011100 4
b10000100 %
b10000100 3
b10000100 .
0$
#1365000
1$
#1370000
b10011010 &
b10011010 4
b10000101 %
b10000101 3
b10000101 .
0$
#1375000
1$
#1380000
b11111101 &
b11111101 4
b10000110 %
b10000110 3
b10000110 .
0$
#1385000
1$
#1390000
b11000011 &
b11000011 4
b10000111 %
b10000111 3
b10000111 .
0$
#1395000
1$
#1400000
b1010110 &
b1010110 4
b10001000 %
b10001000 3
b10001000 .
0$
#1405000
1$
#1410000
b1001110 &
b1001110 4
b10001001 %
b10001001 3
b10001001 .
0$
#1415000
1$
#1420000
b1100111 &
b1100111 4
b10001010 %
b10001010 3
b10001010 .
0$
#1425000
1$
#1430000
b1010 &
b1010 4
b10001011 %
b10001011 3
b10001011 .
0$
#1435000
1$
#1440000
b10110110 &
b10110110 4
b10001100 %
b10001100 3
b10001100 .
0$
#1445000
1$
#1450000
b111000 &
b111000 4
b10001101 %
b10001101 3
b10001101 .
0$
#1455000
1$
#1460000
b1111001 &
b1111001 4
b10001110 %
b10001110 3
b10001110 .
0$
#1465000
1$
#1470000
b10111000 &
b10111000 4
b10001111 %
b10001111 3
b10001111 .
0$
#1475000
1$
#1480000
b10010100 &
b10010100 4
b10010000 %
b10010000 3
b10010000 .
0$
#1485000
1$
#1490000
b10010011 &
b10010011 4
b10010001 %
b10010001 3
b10010001 .
0$
#1495000
1$
#1500000
b100 &
b100 4
b10010010 %
b10010010 3
b10010010 .
0$
#1505000
1$
#1510000
b1011001 &
b1011001 4
b10010011 %
b10010011 3
b10010011 .
0$
#1515000
1$
#1520000
b11011011 &
b11011011 4
b10010100 %
b10010100 3
b10010100 .
0$
#1525000
1$
#1530000
b1001101 &
b1001101 4
b10010101 %
b10010101 3
b10010101 .
0$
#1535000
1$
#1540000
b11011001 &
b11011001 4
b10010110 %
b10010110 3
b10010110 .
0$
#1545000
1$
#1550000
b1101101 &
b1101101 4
b10010111 %
b10010111 3
b10010111 .
0$
#1555000
1$
#1560000
b1110110 &
b1110110 4
b10011000 %
b10011000 3
b10011000 .
0$
#1565000
1$
#1570000
b11001010 &
b11001010 4
b10011001 %
b10011001 3
b10011001 .
0$
#1575000
1$
#1580000
b10110110 &
b10110110 4
b10011010 %
b10011010 3
b10011010 .
0$
#1585000
1$
#1590000
b10010101 &
b10010101 4
b10011011 %
b10011011 3
b10011011 .
0$
#1595000
1$
#1600000
b1000110 &
b1000110 4
b10011100 %
b10011100 3
b10011100 .
0$
#1605000
1$
#1610000
b100 &
b100 4
b10011101 %
b10011101 3
b10011101 .
0$
#1615000
1$
#1620000
b11110111 &
b11110111 4
b10011110 %
b10011110 3
b10011110 .
0$
#1625000
1$
#1630000
b1101001 &
b1101001 4
b10011111 %
b10011111 3
b10011111 .
0$
#1635000
1$
#1640000
b10110100 &
b10110100 4
b10100000 %
b10100000 3
b10100000 .
0$
#1645000
1$
#1650000
b10001000 &
b10001000 4
b10100001 %
b10100001 3
b10100001 .
0$
#1655000
1$
#1660000
b101000 &
b101000 4
b10100010 %
b10100010 3
b10100010 .
0$
#1665000
1$
#1670000
b101101 &
b101101 4
b10100011 %
b10100011 3
b10100011 .
0$
#1675000
1$
#1680000
b11000111 &
b11000111 4
b10100100 %
b10100100 3
b10100100 .
0$
#1685000
1$
#1690000
b101110 &
b101110 4
b10100101 %
b10100101 3
b10100101 .
0$
#1695000
1$
#1700000
b1000 &
b1000 4
b10100110 %
b10100110 3
b10100110 .
0$
#1705000
1$
#1710000
b11100 &
b11100 4
b10100111 %
b10100111 3
b10100111 .
0$
#1715000
1$
#1720000
b11111101 &
b11111101 4
b10101000 %
b10101000 3
b10101000 .
0$
#1725000
1$
#1730000
b101001 &
b101001 4
b10101001 %
b10101001 3
b10101001 .
0$
#1735000
1$
#1740000
b11100 &
b11100 4
b10101010 %
b10101010 3
b10101010 .
0$
#1745000
1$
#1750000
b10000110 &
b10000110 4
b10101011 %
b10101011 3
b10101011 .
0$
#1755000
1$
#1760000
b11011010 &
b11011010 4
b10101100 %
b10101100 3
b10101100 .
0$
#1765000
1$
#1770000
b111101 &
b111101 4
b10101101 %
b10101101 3
b10101101 .
0$
#1775000
1$
#1780000
b1100110 &
b1100110 4
b10101110 %
b10101110 3
b10101110 .
0$
#1785000
1$
#1790000
b1110000 &
b1110000 4
b10101111 %
b10101111 3
b10101111 .
0$
#1795000
1$
#1800000
b1110011 &
b1110011 4
b10110000 %
b10110000 3
b10110000 .
0$
#1805000
1$
#1810000
b10111010 &
b10111010 4
b10110001 %
b10110001 3
b10110001 .
0$
#1815000
1$
#1820000
b1011110 &
b1011110 4
b10110010 %
b10110010 3
b10110010 .
0$
#1825000
1$
#1830000
b11111010 &
b11111010 4
b10110011 %
b10110011 3
b10110011 .
0$
#1835000
1$
#1840000
b11010101 &
b11010101 4
b10110100 %
b10110100 3
b10110100 .
0$
#1845000
1$
#1850000
b11010 &
b11010 4
b10110101 %
b10110101 3
b10110101 .
0$
#1855000
1$
#1860000
b10111001 &
b10111001 4
b10110110 %
b10110110 3
b10110110 .
0$
#1865000
1$
#1870000
b110111 &
b110111 4
b10110111 %
b10110111 3
b10110111 .
0$
#1875000
1$
#1880000
b10010110 &
b10010110 4
b10111000 %
b10111000 3
b10111000 .
0$
#1885000
1$
#1890000
b11000000 &
b11000000 4
b10111001 %
b10111001 3
b10111001 .
0$
#1895000
1$
#1900000
b100110 &
b100110 4
b10111010 %
b10111010 3
b10111010 .
0$
#1905000
1$
#1910000
b10110110 &
b10110110 4
b10111011 %
b10111011 3
b10111011 .
0$
#1915000
1$
#1920000
b1111101 &
b1111101 4
b10111100 %
b10111100 3
b10111100 .
0$
#1925000
1$
#1930000
b11011100 &
b11011100 4
b10111101 %
b10111101 3
b10111101 .
0$
#1935000
1$
#1940000
b10000110 &
b10000110 4
b10111110 %
b10111110 3
b10111110 .
0$
#1945000
1$
#1950000
b1111000 &
b1111000 4
b10111111 %
b10111111 3
b10111111 .
0$
#1955000
1$
#1960000
b1111110 &
b1111110 4
b11000000 %
b11000000 3
b11000000 .
0$
#1965000
1$
#1970000
b11011011 &
b11011011 4
b11000001 %
b11000001 3
b11000001 .
0$
#1975000
1$
#1980000
b11001111 &
b11001111 4
b11000010 %
b11000010 3
b11000010 .
0$
#1985000
1$
#1990000
b1111001 &
b1111001 4
b11000011 %
b11000011 3
b11000011 .
0$
#1995000
1$
#2000000
b11111010 &
b11111010 4
b11000100 %
b11000100 3
b11000100 .
0$
#2005000
1$
#2010000
b1100001 &
b1100001 4
b11000101 %
b11000101 3
b11000101 .
0$
#2015000
1$
#2020000
b10111 &
b10111 4
b11000110 %
b11000110 3
b11000110 .
0$
#2025000
1$
#2030000
b10100001 &
b10100001 4
b11000111 %
b11000111 3
b11000111 .
0$
#2035000
1$
#2040000
b10000110 &
b10000110 4
b11001000 %
b11001000 3
b11001000 .
0$
#2045000
1$
#2050000
b1010000 &
b1010000 4
b11001001 %
b11001001 3
b11001001 .
0$
#2055000
1$
#2060000
b11110101 &
b11110101 4
b11001010 %
b11001010 3
b11001010 .
0$
#2065000
1$
#2070000
b110101 &
b110101 4
b11001011 %
b11001011 3
b11001011 .
0$
#2075000
1$
#2080000
b101001 &
b101001 4
b11001100 %
b11001100 3
b11001100 .
0$
#2085000
1$
#2090000
b11000001 &
b11000001 4
b11001101 %
b11001101 3
b11001101 .
0$
#2095000
1$
#2100000
b11000101 &
b11000101 4
b11001110 %
b11001110 3
b11001110 .
0$
#2105000
1$
#2110000
b10011000 &
b10011000 4
b11001111 %
b11001111 3
b11001111 .
0$
#2115000
1$
#2120000
b1001011 &
b1001011 4
b11010000 %
b11010000 3
b11010000 .
0$
#2125000
1$
#2130000
b1110011 &
b1110011 4
b11010001 %
b11010001 3
b11010001 .
0$
#2135000
1$
#2140000
b11101100 &
b11101100 4
b11010010 %
b11010010 3
b11010010 .
0$
#2145000
1$
#2150000
b10001010 &
b10001010 4
b11010011 %
b11010011 3
b11010011 .
0$
#2155000
1$
#2160000
b1001110 &
b1001110 4
b11010100 %
b11010100 3
b11010100 .
0$
#2165000
1$
#2170000
b10101000 &
b10101000 4
b11010101 %
b11010101 3
b11010101 .
0$
#2175000
1$
#2180000
b10101001 &
b10101001 4
b11010110 %
b11010110 3
b11010110 .
0$
#2185000
1$
#2190000
b10100001 &
b10100001 4
b11010111 %
b11010111 3
b11010111 .
0$
#2195000
1$
#2200000
b1110 &
b1110 4
b11011000 %
b11011000 3
b11011000 .
0$
#2205000
1$
#2210000
b11100110 &
b11100110 4
b11011001 %
b11011001 3
b11011001 .
0$
#2215000
1$
#2220000
b10011111 &
b10011111 4
b11011010 %
b11011010 3
b11011010 .
0$
#2225000
1$
#2230000
b101010 &
b101010 4
b11011011 %
b11011011 3
b11011011 .
0$
#2235000
1$
#2240000
b11011100 %
b11011100 3
b11011100 .
0$
#2245000
1$
#2250000
b10001101 &
b10001101 4
b11011101 %
b11011101 3
b11011101 .
0$
#2255000
1$
#2260000
b10011110 &
b10011110 4
b11011110 %
b11011110 3
b11011110 .
0$
#2265000
1$
#2270000
b111000 &
b111000 4
b11011111 %
b11011111 3
b11011111 .
0$
#2275000
1$
#2280000
b1111001 &
b1111001 4
b11100000 %
b11100000 3
b11100000 .
0$
#2285000
1$
#2290000
b11001000 &
b11001000 4
b11100001 %
b11100001 3
b11100001 .
0$
#2295000
1$
#2300000
b11001010 &
b11001010 4
b11100010 %
b11100010 3
b11100010 .
0$
#2305000
1$
#2310000
b10011 &
b10011 4
b11100011 %
b11100011 3
b11100011 .
0$
#2315000
1$
#2320000
b1101011 &
b1101011 4
b11100100 %
b11100100 3
b11100100 .
0$
#2325000
1$
#2330000
b11000111 &
b11000111 4
b11100101 %
b11100101 3
b11100101 .
0$
#2335000
1$
#2340000
b10110110 &
b10110110 4
b11100110 %
b11100110 3
b11100110 .
0$
#2345000
1$
#2350000
b10111010 &
b10111010 4
b11100111 %
b11100111 3
b11100111 .
0$
#2355000
1$
#2360000
b11000100 &
b11000100 4
b11101000 %
b11101000 3
b11101000 .
0$
#2365000
1$
#2370000
b10111001 &
b10111001 4
b11101001 %
b11101001 3
b11101001 .
0$
#2375000
1$
#2380000
b10010010 &
b10010010 4
b11101010 %
b11101010 3
b11101010 .
0$
#2385000
1$
#2390000
b10110100 &
b10110100 4
b11101011 %
b11101011 3
b11101011 .
0$
#2395000
1$
#2400000
b1111111 &
b1111111 4
b11101100 %
b11101100 3
b11101100 .
0$
#2405000
1$
